[{"codReg":18,"tipoStazione":3,"dettZoomStaz":[],"pstaz":[],"mappaCitta":{"urlImagePinpoint":"","urlImageBaloon":""},"codiceStazione":"S09813","codStazione":"S09813","lat":40.74654,"lon":14.616996,"latMappaCitta":0.0,"lonMappaCitta":0.0,"localita":{"nomeLungo":"PAGANI","nomeBreve":"Pagani","label":"","id":"S09813"},"esterno":false,"offsetX":0,"offsetY":0,"nomeCitta":"A"},{"codReg":18,"tipoStazione":3,"dettZoomStaz":[],"pstaz":[],"mappaCitta":{"urlImagePinpoint":"","urlImageBaloon":""},"codiceStazione":"S09826","codStazione":"S09826","lat":40.630046,"lon":15.235486,"latMappaCitta":0.0,"lonMappaCitta":0.0,"localita":{"nomeLungo":"CONTURSI TERME","nomeBreve":"Contursi Terme","label":"","id":"S09826"},"esterno":false,"offsetX":0,"offsetY":0,"nomeCitta":"A"},{"codReg":18,"tipoStazione":4,"dettZoomStaz":[{"codiceStazione":"S11420","zoomStartRange":8,"zoomStopRange":9,"pinpointVisibile":true,"pinpointVisible":true,"labelVisibile":true,"labelVisible":true,"codiceRegione":null},{"codiceStazione":"S11420","zoomStartRange":10,"zoomStopRange":11,"pinpointVisibile":true,"pinpointVisible":true,"labelVisibile":true,"labelVisible":true,"codiceRegione":null}],"pstaz":[],"mappaCitta":{"urlImagePinpoint":"","urlImageBaloon":""},"codiceStazione":"S11420","codStazione":"S11420","lat":40.629469,"lon":15.806808,"latMappaCitta":0.0,"lonMappaCitta":0.0,"localita":{"nomeLungo":"POTENZA INFERIORE","nomeBreve":"Potenza Inf.re","label":"Potenza","id":"S11420"},"esterno":true,"offsetX":-4,"offsetY":18,"nomeCitta":"Potenza"},{"codReg":18,"tipoStazione":3,"dettZoomStaz":[{"codiceStazione":"S09714","zoomStartRange":8,"zoomStopRange":9,"pinpointVisibile":true,"pinpointVisible":true,"labelVisibile":false,"labelVisible":false,"codiceRegione":null},{"codiceStazione":"S09714","zoomStartRange":10,"zoomStopRange":11,"pinpointVisibile":true,"pinpointVisible":true,"labelVisibile":true,"labelVisible":true,"codiceRegione":null}],"pstaz":[],"mappaCitta":{"urlImagePinpoint":"","urlImageBaloon":""},"codiceStazione":"S09714","codStazione":"S09714","lat":40.742888,"lon":14.682744,"latMappaCitta":0.0,"lonMappaCitta":0.0,"localita":{"nomeLungo":"BIVIO S.LUCIA (NA)","nomeBreve":"Biv. S.Lucia 123","label":"","id":"S09714"},"esterno":false,"offsetX":-4,"offsetY":18,"nomeCitta":"Bivio S.Lucia"},{"codReg":18,"tipoStazione":3,"dettZoomStaz":[],"pstaz":[],"mappaCitta":{"urlImagePinpoint":"","urlImageBaloon":""},"codiceStazione":"S09102","codStazione":"S09102","lat":40.819444,"lon":14.166694,"latMappaCitta":0.0,"lonMappaCitta":0.0,"localita":{"nomeLungo":"BAGNOLI AGNANO TERME","nomeBreve":"Bagnoli Agnano T","label":"","id":"S09102"},"esterno":false,"offsetX":0,"offsetY":0,"nomeCitta":"A"},{"codReg":18,"tipoStazione":3,"dettZoomStaz":[],"pstaz":[],"mappaCitta":{"urlImagePinpoint":"","urlImageBaloon":""},"codiceStazione":"S09004","codStazione":"S09004","lat":40.996117,"lon":14.128596,"latMappaCitta":0.0,"lonMappaCitta":0.0,"localita":{"nomeLungo":"ALBANOVA","nomeBreve":"Albanova","label":"","id":"S09004"},"esterno":false,"offsetX":0,"offsetY":0,"nomeCitta":"A"},{"codReg":18,"tipoStazione":3,"dettZoomStaz":[],"pstaz":[],"mappaCitta":{"urlImagePinpoint":"","urlImageBaloon":""},"codiceStazione":"S09304","codStazione":"S09304","lat":41.087558,"lon":14.426049,"latMappaCitta":0.0,"lonMappaCitta":0.0,"localita":{"nomeLungo":"VALLE DI MADDALONI","nomeBreve":"Valle di Maddal.","label":"","id":"S09304"},"esterno":false,"offsetX":0,"offsetY":0,"nomeCitta":"A"},{"codReg":18,"tipoStazione":3,"dettZoomStaz":[],"pstaz":[],"mappaCitta":{"urlImagePinpoint":"","urlImageBaloon":""},"codiceStazione":"S09900","codStazione":"S09900","lat":40.569272,"lon":15.355627,"latMappaCitta":0.0,"lonMappaCitta":0.0,"localita":{"nomeLungo":"GALDO","nomeBreve":"Galdo","label":"","id":"S09900"},"esterno":false,"offsetX":0,"offsetY":0,"nomeCitta":"A"},{"codReg":18,"tipoStazione":3,"dettZoomStaz":[],"pstaz":[],"mappaCitta":{"urlImagePinpoint":"","urlImageBaloon":""},"codiceStazione":"S09909","codStazione":"S09909","lat":40.286725,"lon":15.653794,"latMappaCitta":0.0,"lonMappaCitta":0.0,"localita":{"nomeLungo":"MONTESANO BUONABITACOLO","nomeBreve":"Montesano B.","label":"","id":"S09909"},"esterno":false,"offsetX":0,"offsetY":0,"nomeCitta":"A"},{"codReg":18,"tipoStazione":3,"dettZoomStaz":[],"pstaz":[],"mappaCitta":{"urlImagePinpoint":"","urlImageBaloon":""},"codiceStazione":"S09907","codStazione":"S09907","lat":40.368687,"lon":15.604818,"latMappaCitta":0.0,"lonMappaCitta":0.0,"localita":{"nomeLungo":"SASSANO TEGGIANO","nomeBreve":"Sassano Teggiano","label":"","id":"S09907"},"esterno":false,"offsetX":0,"offsetY":0,"nomeCitta":"A"},{"codReg":18,"tipoStazione":3,"dettZoomStaz":[],"pstaz":[],"mappaCitta":{"urlImagePinpoint":"","urlImageBaloon":""},"codiceStazione":"S09216","codStazione":"S09216","lat":40.915559,"lon":14.35296,"latMappaCitta":0.0,"lonMappaCitta":0.0,"localita":{"nomeLungo":"CASALNUOVO","nomeBreve":"Casalnuovo","label":"","id":"S09216"},"esterno":false,"offsetX":0,"offsetY":0,"nomeCitta":"A"},{"codReg":18,"tipoStazione":3,"dettZoomStaz":[],"pstaz":[],"mappaCitta":{"urlImagePinpoint":"","urlImageBaloon":""},"codiceStazione":"S09828","codStazione":"S09828","lat":40.600806,"lon":15.374199,"latMappaCitta":0.0,"lonMappaCitta":0.0,"localita":{"nomeLungo":"BUCCINO S.","nomeBreve":"Buccino","label":"","id":"S09828"},"esterno":false,"offsetX":0,"offsetY":0,"nomeCitta":"A"},{"codReg":18,"tipoStazione":3,"dettZoomStaz":[],"pstaz":[],"mappaCitta":{"urlImagePinpoint":"","urlImageBaloon":""},"codiceStazione":"S11703","codStazione":"S11703","lat":40.421691,"lon":15.014915,"latMappaCitta":0.0,"lonMappaCitta":0.0,"localita":{"nomeLungo":"PAESTUM","nomeBreve":"Paestum","label":"","id":"S11703"},"esterno":false,"offsetX":0,"offsetY":0,"nomeCitta":"A"},{"codReg":18,"tipoStazione":3,"dettZoomStaz":[],"pstaz":[],"mappaCitta":{"urlImagePinpoint":"","urlImageBaloon":""},"codiceStazione":"S11706","codStazione":"S11706","lat":40.315916,"lon":15.041267,"latMappaCitta":0.0,"lonMappaCitta":0.0,"localita":{"nomeLungo":"TORCHIARA","nomeBreve":"Torchiara","label":"","id":"S11706"},"esterno":false,"offsetX":0,"offsetY":0,"nomeCitta":"A"},{"codReg":18,"tipoStazione":3,"dettZoomStaz":[],"pstaz":[],"mappaCitta":{"urlImagePinpoint":"","urlImageBaloon":""},"codiceStazione":"S09104","codStazione":"S09104","lat":40.82397,"lon":14.199117,"latMappaCitta":0.0,"lonMappaCitta":0.0,"localita":{"nomeLungo":"NAPOLI PIAZZA LEOPARDI","nomeBreve":"NA P. Leopardi","label":"","id":"S09104"},"esterno":false,"offsetX":0,"offsetY":0,"nomeCitta":"A"},{"codReg":18,"tipoStazione":3,"dettZoomStaz":[],"pstaz":[],"mappaCitta":{"urlImagePinpoint":"","urlImageBaloon":""},"codiceStazione":"S09108","codStazione":"S09108","lat":40.855248,"lon":14.255175,"latMappaCitta":0.0,"lonMappaCitta":0.0,"localita":{"nomeLungo":"PIAZZA CAVOUR","nomeBreve":"Piazza Cavour","label":"","id":"S09108"},"esterno":false,"offsetX":0,"offsetY":0,"nomeCitta":"A"},{"codReg":18,"tipoStazione":4,"dettZoomStaz":[{"codiceStazione":"S09200","zoomStartRange":8,"zoomStopRange":9,"pinpointVisibile":true,"pinpointVisible":true,"labelVisibile":true,"labelVisible":true,"codiceRegione":null},{"codiceStazione":"S09200","zoomStartRange":10,"zoomStopRange":11,"pinpointVisibile":true,"pinpointVisible":true,"labelVisibile":true,"labelVisible":true,"codiceRegione":null}],"pstaz":[],"mappaCitta":{"urlImagePinpoint":"","urlImageBaloon":""},"codiceStazione":"S09200","codStazione":"S09200","lat":41.438861,"lon":13.911338,"latMappaCitta":0.0,"lonMappaCitta":0.0,"localita":{"nomeLungo":"ROCCA D`EVANDRO","nomeBreve":"ROCCA D'EVAN.","label":"","id":"S09200"},"esterno":true,"offsetX":100,"offsetY":20,"nomeCitta":"Rocca d`Evandro"},{"codReg":18,"tipoStazione":3,"dettZoomStaz":[{"codiceStazione":"S09203","zoomStartRange":8,"zoomStopRange":9,"pinpointVisibile":true,"pinpointVisible":true,"labelVisibile":false,"labelVisible":false,"codiceRegione":null},{"codiceStazione":"S09203","zoomStartRange":10,"zoomStopRange":11,"pinpointVisibile":true,"pinpointVisible":true,"labelVisibile":true,"labelVisible":true,"codiceRegione":null}],"pstaz":[],"mappaCitta":{"urlImagePinpoint":"","urlImageBaloon":""},"codiceStazione":"S09203","codStazione":"S09203","lat":41.317446,"lon":14.104022,"latMappaCitta":0.0,"lonMappaCitta":0.0,"localita":{"nomeLungo":"VAIRANO","nomeBreve":"Vairano","label":"","id":"S09203"},"esterno":false,"offsetX":-4,"offsetY":10,"nomeCitta":"Vairano"},{"codReg":18,"tipoStazione":3,"dettZoomStaz":[],"pstaz":[],"mappaCitta":{"urlImagePinpoint":"","urlImageBaloon":""},"codiceStazione":"S09206","codStazione":"S09206","lat":41.185707,"lon":14.092954,"latMappaCitta":0.0,"lonMappaCitta":0.0,"localita":{"nomeLungo":"SPARANISE","nomeBreve":"Sparanise","label":"","id":"S09206"},"esterno":false,"offsetX":0,"offsetY":0,"nomeCitta":"A"},{"codReg":18,"tipoStazione":3,"dettZoomStaz":[],"pstaz":[],"mappaCitta":{"urlImagePinpoint":"","urlImageBaloon":""},"codiceStazione":"S09212","codStazione":"S09212","lat":41.035954,"lon":14.380504,"latMappaCitta":0.0,"lonMappaCitta":0.0,"localita":{"nomeLungo":"MADDALONI INFERIORE","nomeBreve":"Maddaloni Inf.","label":"","id":"S09212"},"esterno":false,"offsetX":0,"offsetY":0,"nomeCitta":"A"},{"codReg":18,"tipoStazione":3,"dettZoomStaz":[{"codiceStazione":"S09300","zoomStartRange":8,"zoomStopRange":9,"pinpointVisibile":true,"pinpointVisible":true,"labelVisibile":false,"labelVisible":false,"codiceRegione":null},{"codiceStazione":"S09300","zoomStartRange":10,"zoomStopRange":11,"pinpointVisibile":true,"pinpointVisible":true,"labelVisibile":true,"labelVisible":true,"codiceRegione":null}],"pstaz":[],"mappaCitta":{"urlImagePinpoint":"","urlImageBaloon":""},"codiceStazione":"S09300","codStazione":"S09300","lat":40.998742,"lon":14.241657,"latMappaCitta":0.0,"lonMappaCitta":0.0,"localita":{"nomeLungo":"GRICIGNANO","nomeBreve":"Gricignano","label":"","id":"S09300"},"esterno":false,"offsetX":60,"offsetY":18,"nomeCitta":"Gricignano"},{"codReg":18,"tipoStazione":3,"dettZoomStaz":[],"pstaz":[],"mappaCitta":{"urlImagePinpoint":"","urlImageBaloon":""},"codiceStazione":"S09306","codStazione":"S09306","lat":41.173509,"lon":14.470759,"latMappaCitta":0.0,"lonMappaCitta":0.0,"localita":{"nomeLungo":"AMOROSI MELIZZANO","nomeBreve":"Amorosi Mel.","label":"","id":"S09306"},"esterno":false,"offsetX":0,"offsetY":0,"nomeCitta":"A"},{"codReg":18,"tipoStazione":3,"dettZoomStaz":[],"pstaz":[],"mappaCitta":{"urlImagePinpoint":"","urlImageBaloon":""},"codiceStazione":"S09309","codStazione":"S09309","lat":41.214169,"lon":14.696458,"latMappaCitta":0.0,"lonMappaCitta":0.0,"localita":{"nomeLungo":"PONTE CASALDUNI","nomeBreve":"Ponte Casalduni","label":"","id":"S09309"},"esterno":false,"offsetX":0,"offsetY":0,"nomeCitta":"A"},{"codReg":18,"tipoStazione":3,"dettZoomStaz":[],"pstaz":[],"mappaCitta":{"urlImagePinpoint":"","urlImageBaloon":""},"codiceStazione":"S09313","codStazione":"S09313","lat":41.146232,"lon":14.838878,"latMappaCitta":0.0,"lonMappaCitta":0.0,"localita":{"nomeLungo":"PADULI","nomeBreve":"Paduli","label":"","id":"S09313"},"esterno":false,"offsetX":0,"offsetY":0,"nomeCitta":"A"},{"codReg":18,"tipoStazione":3,"dettZoomStaz":[],"pstaz":[],"mappaCitta":{"urlImagePinpoint":"","urlImageBaloon":""},"codiceStazione":"S09315","codStazione":"S09315","lat":41.2211,"lon":14.9795,"latMappaCitta":0.0,"lonMappaCitta":0.0,"localita":{"nomeLungo":"MONTECALVO BUONALBERGO CASALB.","nomeBreve":"Montecalvo B.C.","label":"","id":"S09315"},"esterno":false,"offsetX":0,"offsetY":0,"nomeCitta":"A"},{"codReg":18,"tipoStazione":3,"dettZoomStaz":[],"pstaz":[],"mappaCitta":{"urlImagePinpoint":"","urlImageBaloon":""},"codiceStazione":"S09326","codStazione":"S09326","lat":41.211709,"lon":14.526165,"latMappaCitta":0.0,"lonMappaCitta":0.0,"localita":{"nomeLungo":"TELESE CERRETO","nomeBreve":"Telese Cerreto","label":"","id":"S09326"},"esterno":false,"offsetX":0,"offsetY":0,"nomeCitta":"A"},{"codReg":18,"tipoStazione":4,"dettZoomStaz":[{"codiceStazione":"S09452","zoomStartRange":8,"zoomStopRange":9,"pinpointVisibile":true,"pinpointVisible":true,"labelVisibile":true,"labelVisible":true,"codiceRegione":null},{"codiceStazione":"S09452","zoomStartRange":10,"zoomStopRange":11,"pinpointVisibile":true,"pinpointVisible":true,"labelVisibile":true,"labelVisible":true,"codiceRegione":null}],"pstaz":[],"mappaCitta":{"urlImagePinpoint":"","urlImageBaloon":""},"codiceStazione":"S09452","codStazione":"S09452","lat":41.459299,"lon":14.587884,"latMappaCitta":0.0,"lonMappaCitta":0.0,"localita":{"nomeLungo":"BOSCO REDOLE","nomeBreve":"Bosco Redole","label":"","id":"S09452"},"esterno":true,"offsetX":-4,"offsetY":10,"nomeCitta":"Bosco Redole"},{"codReg":18,"tipoStazione":3,"dettZoomStaz":[],"pstaz":[],"mappaCitta":{"urlImagePinpoint":"","urlImageBaloon":""},"codiceStazione":"S09506","codStazione":"S09506","lat":41.247292,"lon":14.76486,"latMappaCitta":0.0,"lonMappaCitta":0.0,"localita":{"nomeLungo":"FRAGNETO MONFORTE","nomeBreve":"Fragneto Monf.","label":"","id":"S09506"},"esterno":false,"offsetX":0,"offsetY":0,"nomeCitta":"A"},{"codReg":18,"tipoStazione":3,"dettZoomStaz":[],"pstaz":[],"mappaCitta":{"urlImagePinpoint":"","urlImageBaloon":""},"codiceStazione":"S09507","codStazione":"S09507","lat":41.236154,"lon":14.788527,"latMappaCitta":0.0,"lonMappaCitta":0.0,"localita":{"nomeLungo":"PESCOSANNITA FRAGNETO L`ABATE","nomeBreve":"Pescosannita F.","label":"","id":"S09507"},"esterno":false,"offsetX":0,"offsetY":0,"nomeCitta":"A"},{"codReg":18,"tipoStazione":3,"dettZoomStaz":[],"pstaz":[],"mappaCitta":{"urlImagePinpoint":"","urlImageBaloon":""},"codiceStazione":"S09508","codStazione":"S09508","lat":41.18865,"lon":14.832469,"latMappaCitta":0.0,"lonMappaCitta":0.0,"localita":{"nomeLungo":"PIETRELCINA","nomeBreve":"Pietrelcina","label":"","id":"S09508"},"esterno":false,"offsetX":0,"offsetY":0,"nomeCitta":"A"},{"codReg":18,"tipoStazione":3,"dettZoomStaz":[],"pstaz":[],"mappaCitta":{"urlImagePinpoint":"","urlImageBaloon":""},"codiceStazione":"S09509","codStazione":"S09509","lat":41.123564,"lon":14.784315,"latMappaCitta":0.0,"lonMappaCitta":0.0,"localita":{"nomeLungo":"BENEVENTO PORTA RUFINA","nomeBreve":"BN Porta Rufina","label":"","id":"S09509"},"esterno":false,"offsetX":0,"offsetY":0,"nomeCitta":"A"},{"codReg":18,"tipoStazione":3,"dettZoomStaz":[],"pstaz":[],"mappaCitta":{"urlImagePinpoint":"","urlImageBaloon":""},"codiceStazione":"S09511","codStazione":"S09511","lat":41.015265,"lon":14.782833,"latMappaCitta":0.0,"lonMappaCitta":0.0,"localita":{"nomeLungo":"ALTAVILLA IRPINA","nomeBreve":"Altavilla Irpina","label":"","id":"S09511"},"esterno":false,"offsetX":0,"offsetY":0,"nomeCitta":"A"},{"codReg":18,"tipoStazione":3,"dettZoomStaz":[],"pstaz":[],"mappaCitta":{"urlImagePinpoint":"","urlImageBaloon":""},"codiceStazione":"S09512","codStazione":"S09512","lat":41.013853,"lon":14.815962,"latMappaCitta":0.0,"lonMappaCitta":0.0,"localita":{"nomeLungo":"TUFO","nomeBreve":"Tufo","label":"","id":"S09512"},"esterno":false,"offsetX":0,"offsetY":0,"nomeCitta":"A"},{"codReg":18,"tipoStazione":3,"dettZoomStaz":[],"pstaz":[],"mappaCitta":{"urlImagePinpoint":"","urlImageBaloon":""},"codiceStazione":"S09513","codStazione":"S09513","lat":40.988509,"lon":14.842666,"latMappaCitta":0.0,"lonMappaCitta":0.0,"localita":{"nomeLungo":"PRATA PRATOLA","nomeBreve":"Prata Pratola","label":"","id":"S09513"},"esterno":false,"offsetX":0,"offsetY":0,"nomeCitta":"A"},{"codReg":18,"tipoStazione":3,"dettZoomStaz":[],"pstaz":[],"mappaCitta":{"urlImagePinpoint":"","urlImageBaloon":""},"codiceStazione":"S09524","codStazione":"S09524","lat":40.697895,"lon":14.779252,"latMappaCitta":0.0,"lonMappaCitta":0.0,"localita":{"nomeLungo":"FRATTE VILLA COMUNALE","nomeBreve":"Fratte-Villa Com","label":"","id":"S09524"},"esterno":false,"offsetX":0,"offsetY":0,"nomeCitta":"A"},{"codReg":18,"tipoStazione":3,"dettZoomStaz":[],"pstaz":[],"mappaCitta":{"urlImagePinpoint":"","urlImageBaloon":""},"codiceStazione":"S09603","codStazione":"S09603","lat":40.993606,"lon":14.920685,"latMappaCitta":0.0,"lonMappaCitta":0.0,"localita":{"nomeLungo":"MONTEMILETTO","nomeBreve":"Montemiletto","label":"","id":"S09603"},"esterno":false,"offsetX":0,"offsetY":0,"nomeCitta":"A"},{"codReg":18,"tipoStazione":3,"dettZoomStaz":[],"pstaz":[],"mappaCitta":{"urlImagePinpoint":"","urlImageBaloon":""},"codiceStazione":"S09608","codStazione":"S09608","lat":40.952072,"lon":15.011348,"latMappaCitta":0.0,"lonMappaCitta":0.0,"localita":{"nomeLungo":"CASTELVETERE","nomeBreve":"Castelvetere","label":"","id":"S09608"},"esterno":false,"offsetX":0,"offsetY":0,"nomeCitta":"A"},{"codReg":18,"tipoStazione":3,"dettZoomStaz":[],"pstaz":[],"mappaCitta":{"urlImagePinpoint":"","urlImageBaloon":""},"codiceStazione":"S09617","codStazione":"S09617","lat":40.890563,"lon":15.239328,"latMappaCitta":0.0,"lonMappaCitta":0.0,"localita":{"nomeLungo":"MORRA DE SANCTIS TEORA","nomeBreve":"Morra de S.T.","label":"","id":"S09617"},"esterno":false,"offsetX":0,"offsetY":0,"nomeCitta":"A"},{"codReg":18,"tipoStazione":3,"dettZoomStaz":[],"pstaz":[],"mappaCitta":{"urlImagePinpoint":"","urlImageBaloon":""},"codiceStazione":"S09629","codStazione":"S09629","lat":40.8869,"lon":15.27783,"latMappaCitta":0.0,"lonMappaCitta":0.0,"localita":{"nomeLungo":"SANZANO OCCHINO","nomeBreve":"Sanzano Occhino","label":"","id":"S09629"},"esterno":false,"offsetX":0,"offsetY":0,"nomeCitta":"A"},{"codReg":18,"tipoStazione":3,"dettZoomStaz":[],"pstaz":[],"mappaCitta":{"urlImagePinpoint":"","urlImageBaloon":""},"codiceStazione":"S09701","codStazione":"S09701","lat":40.864149,"lon":14.540472,"latMappaCitta":0.0,"lonMappaCitta":0.0,"localita":{"nomeLungo":"PALMA S.GENNARO","nomeBreve":"Palma S.Gennaro","label":"","id":"S09701"},"esterno":false,"offsetX":0,"offsetY":0,"nomeCitta":"A"},{"codReg":18,"tipoStazione":3,"dettZoomStaz":[],"pstaz":[],"mappaCitta":{"urlImagePinpoint":"","urlImageBaloon":""},"codiceStazione":"S09704","codStazione":"S09704","lat":40.758713,"lon":14.692352,"latMappaCitta":0.0,"lonMappaCitta":0.0,"localita":{"nomeLungo":"CASTEL S.GIORGIO ROCCAPIEMONTE","nomeBreve":"Castel S.Giorgio","label":"","id":"S09704"},"esterno":false,"offsetX":0,"offsetY":0,"nomeCitta":"A"},{"codReg":18,"tipoStazione":3,"dettZoomStaz":[],"pstaz":[],"mappaCitta":{"urlImagePinpoint":"","urlImageBaloon":""},"codiceStazione":"S09705","codStazione":"S09705","lat":40.776365,"lon":14.722362,"latMappaCitta":0.0,"lonMappaCitta":0.0,"localita":{"nomeLungo":"VALLE DI MERCATO S.SEVERINO","nomeBreve":"Valle di Mercato","label":"","id":"S09705"},"esterno":false,"offsetX":0,"offsetY":0,"nomeCitta":"A"},{"codReg":18,"tipoStazione":3,"dettZoomStaz":[],"pstaz":[],"mappaCitta":{"urlImagePinpoint":"","urlImageBaloon":""},"codiceStazione":"S09800","codStazione":"S09800","lat":40.831269,"lon":14.307811,"latMappaCitta":0.0,"lonMappaCitta":0.0,"localita":{"nomeLungo":"NAPOLI S.GIOV.BARRA","nomeBreve":"Napoli S.G.Barra","label":"","id":"S09800"},"esterno":false,"offsetX":0,"offsetY":0,"nomeCitta":"A"},{"codReg":18,"tipoStazione":3,"dettZoomStaz":[],"pstaz":[],"mappaCitta":{"urlImagePinpoint":"","urlImageBaloon":""},"codiceStazione":"S09802","codStazione":"S09802","lat":40.809907,"lon":14.335809,"latMappaCitta":0.0,"lonMappaCitta":0.0,"localita":{"nomeLungo":"PORTICI- ERCOLANO","nomeBreve":"Portici Ercolano","label":"","id":"S09802"},"esterno":false,"offsetX":0,"offsetY":0,"nomeCitta":"A"},{"codReg":18,"tipoStazione":3,"dettZoomStaz":[],"pstaz":[],"mappaCitta":{"urlImagePinpoint":"","urlImageBaloon":""},"codiceStazione":"S09817","codStazione":"S09817","lat":40.674996,"lon":14.726829,"latMappaCitta":0.0,"lonMappaCitta":0.0,"localita":{"nomeLungo":"VIETRI SUL MARE","nomeBreve":"Vietri sul Mare","label":"","id":"S09817"},"esterno":false,"offsetX":0,"offsetY":0,"nomeCitta":"A"},{"codReg":18,"tipoStazione":3,"dettZoomStaz":[],"pstaz":[],"mappaCitta":{"urlImagePinpoint":"","urlImageBaloon":""},"codiceStazione":"S09821","codStazione":"S09821","lat":40.641033,"lon":14.870272,"latMappaCitta":0.0,"lonMappaCitta":0.0,"localita":{"nomeLungo":"PONTECAGNANO","nomeBreve":"Pontecagnano","label":"","id":"S09821"},"esterno":false,"offsetX":0,"offsetY":0,"nomeCitta":"A"},{"codReg":18,"tipoStazione":3,"dettZoomStaz":[],"pstaz":[],"mappaCitta":{"urlImagePinpoint":"","urlImageBaloon":""},"codiceStazione":"S09825","codStazione":"S09825","lat":40.595667,"lon":15.113986,"latMappaCitta":0.0,"lonMappaCitta":0.0,"localita":{"nomeLungo":"CAMPAGNA SERRE PERSANO","nomeBreve":"Campagna S.P.","label":"","id":"S09825"},"esterno":false,"offsetX":0,"offsetY":0,"nomeCitta":"A"},{"codReg":18,"tipoStazione":3,"dettZoomStaz":[],"pstaz":[],"mappaCitta":{"urlImagePinpoint":"","urlImageBaloon":""},"codiceStazione":"S09827","codStazione":"S09827","lat":40.605454,"lon":15.290904,"latMappaCitta":0.0,"lonMappaCitta":0.0,"localita":{"nomeLungo":"SICIGNANO DEGLI ALBURNI","nomeBreve":"Sicignano d.A.","label":"","id":"S09827"},"esterno":false,"offsetX":0,"offsetY":0,"nomeCitta":"A"},{"codReg":18,"tipoStazione":3,"dettZoomStaz":[],"pstaz":[],"mappaCitta":{"urlImagePinpoint":"","urlImageBaloon":""},"codiceStazione":"S09904","codStazione":"S09904","lat":40.456676,"lon":15.536094,"latMappaCitta":0.0,"lonMappaCitta":0.0,"localita":{"nomeLungo":"ATENA","nomeBreve":"Atena","label":"","id":"S09904"},"esterno":false,"offsetX":0,"offsetY":0,"nomeCitta":"A"},{"codReg":18,"tipoStazione":4,"dettZoomStaz":[{"codiceStazione":"S11205","zoomStartRange":8,"zoomStopRange":9,"pinpointVisibile":true,"pinpointVisible":true,"labelVisibile":true,"labelVisible":true,"codiceRegione":null},{"codiceStazione":"S11205","zoomStartRange":10,"zoomStopRange":11,"pinpointVisibile":true,"pinpointVisible":true,"labelVisibile":true,"labelVisible":true,"codiceRegione":null}],"pstaz":[],"mappaCitta":{"urlImagePinpoint":"","urlImageBaloon":""},"codiceStazione":"S11205","codStazione":"S11205","lat":41.1518,"lon":15.53295,"latMappaCitta":0.0,"lonMappaCitta":0.0,"localita":{"nomeLungo":"ROCCHETTA S.ANT.LAC.","nomeBreve":"Rocchetta S.A.L.","label":"","id":"S11205"},"esterno":true,"offsetX":-4,"offsetY":18,"nomeCitta":"Rocchetta S.A.L."},{"codReg":18,"tipoStazione":3,"dettZoomStaz":[],"pstaz":[],"mappaCitta":{"urlImagePinpoint":"","urlImageBaloon":""},"codiceStazione":"S11707","codStazione":"S11707","lat":40.29259,"lon":15.104561,"latMappaCitta":0.0,"lonMappaCitta":0.0,"localita":{"nomeLungo":"RUTINO","nomeBreve":"Rutino","label":"","id":"S11707"},"esterno":false,"offsetX":0,"offsetY":0,"nomeCitta":"A"},{"codReg":18,"tipoStazione":3,"dettZoomStaz":[],"pstaz":[],"mappaCitta":{"urlImagePinpoint":"","urlImageBaloon":""},"codiceStazione":"S11709","codStazione":"S11709","lat":40.233316,"lon":15.266511,"latMappaCitta":0.0,"lonMappaCitta":0.0,"localita":{"nomeLungo":"VALLO DELLA LUC. CASTELNUOVO","nomeBreve":"Vallo d.Lucania","label":"","id":"S11709"},"esterno":false,"offsetX":0,"offsetY":0,"nomeCitta":"A"},{"codReg":18,"tipoStazione":4,"dettZoomStaz":[],"pstaz":[],"mappaCitta":{"urlImagePinpoint":"","urlImageBaloon":""},"codiceStazione":"F00048","codStazione":"F00048","lat":40.785611,"lon":14.620886,"latMappaCitta":0.0,"lonMappaCitta":0.0,"localita":{"nomeLungo":"F00048","nomeBreve":"F00048","label":"","id":"F00048"},"esterno":false,"offsetX":0,"offsetY":0,"nomeCitta":"F00048"},{"codReg":18,"tipoStazione":4,"dettZoomStaz":[{"codiceStazione":"F00026","zoomStartRange":6,"zoomStopRange":11,"pinpointVisibile":false,"pinpointVisible":false,"labelVisibile":false,"labelVisible":false,"codiceRegione":null}],"pstaz":[],"mappaCitta":{"urlImagePinpoint":"","urlImageBaloon":""},"codiceStazione":"F00026","codStazione":"F00026","lat":41.235995,"lon":13.992462,"latMappaCitta":0.0,"lonMappaCitta":0.0,"localita":{"nomeLungo":"F00026","nomeBreve":"F00026","label":"","id":"F00026"},"esterno":false,"offsetX":0,"offsetY":0,"nomeCitta":"F00026"},{"codReg":18,"tipoStazione":3,"dettZoomStaz":[{"codiceStazione":"S09620","zoomStartRange":8,"zoomStopRange":9,"pinpointVisibile":true,"pinpointVisible":true,"labelVisibile":false,"labelVisible":false,"codiceRegione":null},{"codiceStazione":"S09620","zoomStartRange":10,"zoomStopRange":11,"pinpointVisibile":true,"pinpointVisible":true,"labelVisibile":true,"labelVisible":true,"codiceRegione":null}],"pstaz":[],"mappaCitta":{"urlImagePinpoint":"","urlImageBaloon":""},"codiceStazione":"S09620","codStazione":"S09620","lat":40.884932,"lon":15.427962,"latMappaCitta":0.0,"lonMappaCitta":0.0,"localita":{"nomeLungo":"CALITRI PESCOPAGANO","nomeBreve":"Calitri Pescop.","label":"","id":"S09620"},"esterno":false,"offsetX":0,"offsetY":0,"nomeCitta":"Calitri Pescop."},{"codReg":18,"tipoStazione":3,"dettZoomStaz":[],"pstaz":[],"mappaCitta":{"urlImagePinpoint":"","urlImageBaloon":""},"codiceStazione":"S09752","codStazione":"S09752","lat":40.834058,"lon":14.502954,"latMappaCitta":0.0,"lonMappaCitta":0.0,"localita":{"nomeLungo":"S.GIUSEPPE VESUVIANO","nomeBreve":"S.Giuseppe Ves.","label":"","id":"S09752"},"esterno":false,"offsetX":0,"offsetY":0,"nomeCitta":"A"},{"codReg":18,"tipoStazione":3,"dettZoomStaz":[{"codiceStazione":"S09829","zoomStartRange":8,"zoomStopRange":9,"pinpointVisibile":true,"pinpointVisible":true,"labelVisibile":false,"labelVisible":false,"codiceRegione":null},{"codiceStazione":"S09829","zoomStartRange":10,"zoomStopRange":11,"pinpointVisibile":true,"pinpointVisible":true,"labelVisibile":true,"labelVisible":true,"codiceRegione":null}],"pstaz":[],"mappaCitta":{"urlImagePinpoint":"","urlImageBaloon":""},"codiceStazione":"S09829","codStazione":"S09829","lat":40.610041,"lon":15.447651,"latMappaCitta":0.0,"lonMappaCitta":0.0,"localita":{"nomeLungo":"ROMAGNANO V.","nomeBreve":"Romagnano V.","label":"","id":"S09829"},"esterno":false,"offsetX":0,"offsetY":0,"nomeCitta":"Romagnano V."},{"codReg":18,"tipoStazione":3,"dettZoomStaz":[],"pstaz":[],"mappaCitta":{"urlImagePinpoint":"","urlImageBaloon":""},"codiceStazione":"S09523","codStazione":"S09523","lat":40.874511,"lon":14.853445,"latMappaCitta":0.0,"lonMappaCitta":0.0,"localita":{"nomeLungo":"S.MICHELE DI SERINO","nomeBreve":"S.Michele di S.","label":"","id":"S09523"},"esterno":false,"offsetX":0,"offsetY":0,"nomeCitta":"A"},{"codReg":18,"tipoStazione":3,"dettZoomStaz":[],"pstaz":[],"mappaCitta":{"urlImagePinpoint":"","urlImageBaloon":""},"codiceStazione":"S09515","codStazione":"S09515","lat":40.858838,"lon":14.860182,"latMappaCitta":0.0,"lonMappaCitta":0.0,"localita":{"nomeLungo":"SERINO","nomeBreve":"Serino","label":"","id":"S09515"},"esterno":false,"offsetX":0,"offsetY":0,"nomeCitta":"A"},{"codReg":18,"tipoStazione":3,"dettZoomStaz":[],"pstaz":[],"mappaCitta":{"urlImagePinpoint":"","urlImageBaloon":""},"codiceStazione":"S09605","codStazione":"S09605","lat":40.980838,"lon":14.965804,"latMappaCitta":0.0,"lonMappaCitta":0.0,"localita":{"nomeLungo":"TAURASI","nomeBreve":"Taurasi","label":"","id":"S09605"},"esterno":false,"offsetX":0,"offsetY":0,"nomeCitta":"A"},{"codReg":18,"tipoStazione":3,"dettZoomStaz":[],"pstaz":[],"mappaCitta":{"urlImagePinpoint":"","urlImageBaloon":""},"codiceStazione":"S09100","codStazione":"S09100","lat":40.935018,"lon":14.10378,"latMappaCitta":0.0,"lonMappaCitta":0.0,"localita":{"nomeLungo":"GIUGLIANO QUALIANO","nomeBreve":"Giugliano Qual.","label":"","id":"S09100"},"esterno":false,"offsetX":0,"offsetY":0,"nomeCitta":"A"},{"codReg":18,"tipoStazione":3,"dettZoomStaz":[],"pstaz":[],"mappaCitta":{"urlImagePinpoint":"","urlImageBaloon":""},"codiceStazione":"S09837","codStazione":"S09837","lat":40.606491,"lon":15.38979,"latMappaCitta":0.0,"lonMappaCitta":0.0,"localita":{"nomeLungo":"MERCATELLO","nomeBreve":"Mercatello","label":"","id":"S09837"},"esterno":false,"offsetX":0,"offsetY":0,"nomeCitta":"A"},{"codReg":18,"tipoStazione":3,"dettZoomStaz":[],"pstaz":[],"mappaCitta":{"urlImagePinpoint":"","urlImageBaloon":""},"codiceStazione":"S09838","codStazione":"S09838","lat":40.677263,"lon":15.623814,"latMappaCitta":0.0,"lonMappaCitta":0.0,"localita":{"nomeLungo":"ARBOSTELLA","nomeBreve":"Arbostella","label":"","id":"S09838"},"esterno":false,"offsetX":0,"offsetY":0,"nomeCitta":"A"},{"codReg":18,"tipoStazione":3,"dettZoomStaz":[],"pstaz":[],"mappaCitta":{"urlImagePinpoint":"","urlImageBaloon":""},"codiceStazione":"S09615","codStazione":"S09615","lat":40.890372,"lon":15.161478,"latMappaCitta":0.0,"lonMappaCitta":0.0,"localita":{"nomeLungo":"S.ANGELO DEI LOMBARDI","nomeBreve":"S.Angelo dei L.m","label":"","id":"S09615"},"esterno":false,"offsetX":0,"offsetY":0,"nomeCitta":"A"},{"codReg":18,"tipoStazione":3,"dettZoomStaz":[],"pstaz":[],"mappaCitta":{"urlImagePinpoint":"","urlImageBaloon":""},"codiceStazione":"S09007","codStazione":"S09007","lat":40.949188,"lon":14.247415,"latMappaCitta":0.0,"lonMappaCitta":0.0,"localita":{"nomeLungo":"S.ANTIMO S.ARPINO","nomeBreve":"S.Antimo S.Arpin","label":"","id":"S09007"},"esterno":false,"offsetX":0,"offsetY":0,"nomeCitta":"A"},{"codReg":18,"tipoStazione":3,"dettZoomStaz":[],"pstaz":[],"mappaCitta":{"urlImagePinpoint":"","urlImageBaloon":""},"codiceStazione":"S09502","codStazione":"S09502","lat":41.37114,"lon":14.705455,"latMappaCitta":0.0,"lonMappaCitta":0.0,"localita":{"nomeLungo":"S.CROCE DEL SANNIO","nomeBreve":"S.Croce del S.","label":"","id":"S09502"},"esterno":false,"offsetX":0,"offsetY":0,"nomeCitta":"A"},{"codReg":18,"tipoStazione":3,"dettZoomStaz":[],"pstaz":[],"mappaCitta":{"urlImagePinpoint":"","urlImageBaloon":""},"codiceStazione":"S09317","codStazione":"S09317","lat":41.188984,"lon":15.145482,"latMappaCitta":0.0,"lonMappaCitta":0.0,"localita":{"nomeLungo":"PIANEROTTOLO DI ARIANO","nomeBreve":"Pianerottolo A.","label":"","id":"S09317"},"esterno":false,"offsetX":0,"offsetY":0,"nomeCitta":"A"},{"codReg":18,"tipoStazione":3,"dettZoomStaz":[],"pstaz":[],"mappaCitta":{"urlImagePinpoint":"","urlImageBaloon":""},"codiceStazione":"S09801","codStazione":"S09801","lat":40.822433,"lon":14.32058,"latMappaCitta":0.0,"lonMappaCitta":0.0,"localita":{"nomeLungo":"PIETRARSA","nomeBreve":"Pietrarsa","label":"","id":"S09801"},"esterno":false,"offsetX":0,"offsetY":0,"nomeCitta":"A"},{"codReg":18,"tipoStazione":3,"dettZoomStaz":[{"codiceStazione":"S09311","zoomStartRange":8,"zoomStopRange":9,"pinpointVisibile":true,"pinpointVisible":true,"labelVisibile":true,"labelVisible":true,"codiceRegione":null},{"codiceStazione":"S09311","zoomStartRange":10,"zoomStopRange":11,"pinpointVisibile":true,"pinpointVisible":true,"labelVisibile":true,"labelVisible":true,"codiceRegione":null}],"pstaz":[],"mappaCitta":{"urlImagePinpoint":"","urlImageBaloon":""},"codiceStazione":"S09311","codStazione":"S09311","lat":41.141901,"lon":14.769998,"latMappaCitta":0.0,"lonMappaCitta":0.0,"localita":{"nomeLungo":"BENEVENTO","nomeBreve":"Benevento","label":"Benevento","id":"S09311"},"esterno":false,"offsetX":0,"offsetY":0,"nomeCitta":"Benevento"},{"codReg":18,"tipoStazione":3,"dettZoomStaz":[],"pstaz":[],"mappaCitta":{"urlImagePinpoint":"","urlImageBaloon":""},"codiceStazione":"S09602","codStazione":"S09602","lat":40.951114,"lon":14.886432,"latMappaCitta":0.0,"lonMappaCitta":0.0,"localita":{"nomeLungo":"MONTEFALCIONE","nomeBreve":"Montefalcione","label":"","id":"S09602"},"esterno":false,"offsetX":0,"offsetY":0,"nomeCitta":"A"},{"codReg":18,"tipoStazione":3,"dettZoomStaz":[],"pstaz":[],"mappaCitta":{"urlImagePinpoint":"","urlImageBaloon":""},"codiceStazione":"S09529","codStazione":"S09529","lat":40.951143,"lon":14.827771,"latMappaCitta":0.0,"lonMappaCitta":0.0,"localita":{"nomeLungo":"MONTEFREDANE","nomeBreve":"Montefredane","label":"","id":"S09529"},"esterno":false,"offsetX":0,"offsetY":0,"nomeCitta":"A"},{"codReg":18,"tipoStazione":3,"dettZoomStaz":[],"pstaz":[],"mappaCitta":{"urlImagePinpoint":"","urlImageBaloon":""},"codiceStazione":"S09612","codStazione":"S09612","lat":40.845175,"lon":15.032758,"latMappaCitta":0.0,"lonMappaCitta":0.0,"localita":{"nomeLungo":"MONTELLA","nomeBreve":"Montella","label":"","id":"S09612"},"esterno":false,"offsetX":0,"offsetY":0,"nomeCitta":"A"},{"codReg":18,"tipoStazione":3,"dettZoomStaz":[],"pstaz":[],"mappaCitta":{"urlImagePinpoint":"","urlImageBaloon":""},"codiceStazione":"S09610","codStazione":"S09610","lat":40.900728,"lon":15.039506,"latMappaCitta":0.0,"lonMappaCitta":0.0,"localita":{"nomeLungo":"MONTEMARANO","nomeBreve":"Montemarano","label":"","id":"S09610"},"esterno":false,"offsetX":0,"offsetY":0,"nomeCitta":"A"},{"codReg":18,"tipoStazione":3,"dettZoomStaz":[],"pstaz":[],"mappaCitta":{"urlImagePinpoint":"","urlImageBaloon":""},"codiceStazione":"S09305","codStazione":"S09305","lat":41.137244,"lon":14.459459,"latMappaCitta":0.0,"lonMappaCitta":0.0,"localita":{"nomeLungo":"FRASSO T. DUGENTA","nomeBreve":"Frasso Dugenta","label":"","id":"S09305"},"esterno":false,"offsetX":0,"offsetY":0,"nomeCitta":"A"},{"codReg":18,"tipoStazione":3,"dettZoomStaz":[],"pstaz":[],"mappaCitta":{"urlImagePinpoint":"","urlImageBaloon":""},"codiceStazione":"S09008","codStazione":"S09008","lat":40.940018,"lon":14.263676,"latMappaCitta":0.0,"lonMappaCitta":0.0,"localita":{"nomeLungo":"FRATTAMAGGIORE","nomeBreve":"Frattamaggiore","label":"","id":"S09008"},"esterno":false,"offsetX":0,"offsetY":0,"nomeCitta":"A"},{"codReg":18,"tipoStazione":3,"dettZoomStaz":[],"pstaz":[],"mappaCitta":{"urlImagePinpoint":"","urlImageBaloon":""},"codiceStazione":"S09522","codStazione":"S09522","lat":40.705637,"lon":14.778362,"latMappaCitta":0.0,"lonMappaCitta":0.0,"localita":{"nomeLungo":"FRATTE","nomeBreve":"Fratte","label":"","id":"S09522"},"esterno":false,"offsetX":0,"offsetY":0,"nomeCitta":"A"},{"codReg":18,"tipoStazione":3,"dettZoomStaz":[{"codiceStazione":"S09814","zoomStartRange":8,"zoomStopRange":9,"pinpointVisibile":true,"pinpointVisible":true,"labelVisibile":false,"labelVisible":false,"codiceRegione":null},{"codiceStazione":"S09814","zoomStartRange":10,"zoomStopRange":11,"pinpointVisibile":true,"pinpointVisible":true,"labelVisibile":true,"labelVisible":true,"codiceRegione":null}],"pstaz":[],"mappaCitta":{"urlImagePinpoint":"","urlImageBaloon":""},"codiceStazione":"S09814","codStazione":"S09814","lat":40.745318,"lon":14.635346,"latMappaCitta":0.0,"lonMappaCitta":0.0,"localita":{"nomeLungo":"NOCERA INFERIORE","nomeBreve":"Nocera Inferiore","label":"","id":"S09814"},"esterno":false,"offsetX":85,"offsetY":0,"nomeCitta":"Nocera Inferiore"},{"codReg":18,"tipoStazione":3,"dettZoomStaz":[],"pstaz":[],"mappaCitta":{"urlImagePinpoint":"","urlImageBaloon":""},"codiceStazione":"S09709","codStazione":"S09709","lat":40.745668,"lon":14.649129,"latMappaCitta":0.0,"lonMappaCitta":0.0,"localita":{"nomeLungo":"NOCERA INFERIORE MERCATO","nomeBreve":"Nocera Mercato","label":"","id":"S09709"},"esterno":false,"offsetX":0,"offsetY":0,"nomeCitta":"A"},{"codReg":18,"tipoStazione":3,"dettZoomStaz":[],"pstaz":[],"mappaCitta":{"urlImagePinpoint":"","urlImageBaloon":""},"codiceStazione":"S09815","codStazione":"S09815","lat":40.742597,"lon":14.672398,"latMappaCitta":0.0,"lonMappaCitta":0.0,"localita":{"nomeLungo":"NOCERA SUPERIORE","nomeBreve":"Nocera Superiore","label":"","id":"S09815"},"esterno":false,"offsetX":0,"offsetY":0,"nomeCitta":"A"},{"codReg":18,"tipoStazione":3,"dettZoomStaz":[{"codiceStazione":"S09700","zoomStartRange":8,"zoomStopRange":9,"pinpointVisibile":true,"pinpointVisible":true,"labelVisibile":false,"labelVisible":false,"codiceRegione":null},{"codiceStazione":"S09700","zoomStartRange":10,"zoomStopRange":11,"pinpointVisibile":true,"pinpointVisible":true,"labelVisibile":true,"labelVisible":true,"codiceRegione":null}],"pstaz":[],"mappaCitta":{"urlImagePinpoint":"","urlImageBaloon":""},"codiceStazione":"S09700","codStazione":"S09700","lat":40.923652,"lon":14.525004,"latMappaCitta":0.0,"lonMappaCitta":0.0,"localita":{"nomeLungo":"NOLA","nomeBreve":"Nola","label":"","id":"S09700"},"esterno":false,"offsetX":0,"offsetY":0,"nomeCitta":"Nola"},{"codReg":18,"tipoStazione":4,"dettZoomStaz":[{"codiceStazione":"S09320","zoomStartRange":8,"zoomStopRange":9,"pinpointVisibile":true,"pinpointVisible":true,"labelVisibile":true,"labelVisible":true,"codiceRegione":null},{"codiceStazione":"S09320","zoomStartRange":10,"zoomStopRange":11,"pinpointVisibile":true,"pinpointVisible":true,"labelVisibile":true,"labelVisible":true,"codiceRegione":null}],"pstaz":[],"mappaCitta":{"urlImagePinpoint":"","urlImageBaloon":""},"codiceStazione":"S09320","codStazione":"S09320","lat":41.241899,"lon":15.27766,"latMappaCitta":0.0,"lonMappaCitta":0.0,"localita":{"nomeLungo":"ORSARA DI PUGLIA","nomeBreve":"Orsara di Puglia","label":"","id":"S09320"},"esterno":true,"offsetX":93,"offsetY":20,"nomeCitta":"Orsara di Puglia"},{"codReg":18,"tipoStazione":3,"dettZoomStaz":[],"pstaz":[],"mappaCitta":{"urlImagePinpoint":"","urlImageBaloon":""},"codiceStazione":"S09751","codStazione":"S09751","lat":40.85256,"lon":14.493479,"latMappaCitta":0.0,"lonMappaCitta":0.0,"localita":{"nomeLungo":"OTTAVIANO","nomeBreve":"Ottaviano","label":"","id":"S09751"},"esterno":false,"offsetX":0,"offsetY":0,"nomeCitta":"A"},{"codReg":18,"tipoStazione":3,"dettZoomStaz":[{"codiceStazione":"S09806","zoomStartRange":8,"zoomStopRange":9,"pinpointVisibile":true,"pinpointVisible":true,"labelVisibile":false,"labelVisible":false,"codiceRegione":null},{"codiceStazione":"S09806","zoomStartRange":10,"zoomStopRange":11,"pinpointVisibile":true,"pinpointVisible":true,"labelVisibile":true,"labelVisible":true,"codiceRegione":null}],"pstaz":[],"mappaCitta":{"urlImagePinpoint":"","urlImageBaloon":""},"codiceStazione":"S09806","codStazione":"S09806","lat":40.747131,"lon":14.463744,"latMappaCitta":0.0,"lonMappaCitta":0.0,"localita":{"nomeLungo":"TORRE ANNUNZIATA CENTRALE","nomeBreve":"Torre A.Centrale","label":"","id":"S09806"},"esterno":false,"offsetX":110,"offsetY":0,"nomeCitta":"Torre A.Centrale"},{"codReg":18,"tipoStazione":3,"dettZoomStaz":[],"pstaz":[],"mappaCitta":{"urlImagePinpoint":"","urlImageBaloon":""},"codiceStazione":"S09805","codStazione":"S09805","lat":40.754069,"lon":14.448628,"latMappaCitta":0.0,"lonMappaCitta":0.0,"localita":{"nomeLungo":"TORRE ANNUNZIATA CITTA'","nomeBreve":"Torre A. Città","label":"","id":"S09805"},"esterno":false,"offsetX":0,"offsetY":0,"nomeCitta":"A"},{"codReg":18,"tipoStazione":3,"dettZoomStaz":[],"pstaz":[],"mappaCitta":{"urlImagePinpoint":"","urlImageBaloon":""},"codiceStazione":"S09803","codStazione":"S09803","lat":40.787631,"lon":14.363159,"latMappaCitta":0.0,"lonMappaCitta":0.0,"localita":{"nomeLungo":"TORRE DEL GRECO","nomeBreve":"Torre del Greco","label":"","id":"S09803"},"esterno":false,"offsetX":0,"offsetY":0,"nomeCitta":"A"},{"codReg":18,"tipoStazione":3,"dettZoomStaz":[],"pstaz":[],"mappaCitta":{"urlImagePinpoint":"","urlImageBaloon":""},"codiceStazione":"S09616","codStazione":"S09616","lat":40.874869,"lon":15.186324,"latMappaCitta":0.0,"lonMappaCitta":0.0,"localita":{"nomeLungo":"LIONI","nomeBreve":"Lioni","label":"","id":"S09616"},"esterno":false,"offsetX":0,"offsetY":0,"nomeCitta":"A"},{"codReg":18,"tipoStazione":3,"dettZoomStaz":[],"pstaz":[],"mappaCitta":{"urlImagePinpoint":"","urlImageBaloon":""},"codiceStazione":"S09628","codStazione":"S09628","lat":40.887025,"lon":15.215936,"latMappaCitta":0.0,"lonMappaCitta":0.0,"localita":{"nomeLungo":"LIONI VALLE DELLE VITI","nomeBreve":"L.Valle d.Viti","label":"","id":"S09628"},"esterno":false,"offsetX":0,"offsetY":0,"nomeCitta":"A"},{"codReg":18,"tipoStazione":3,"dettZoomStaz":[],"pstaz":[],"mappaCitta":{"urlImagePinpoint":"","urlImageBaloon":""},"codiceStazione":"S09303","codStazione":"S09303","lat":41.048567,"lon":14.396055,"latMappaCitta":0.0,"lonMappaCitta":0.0,"localita":{"nomeLungo":"MADDALONI SUPERIORE","nomeBreve":"Maddaloni Super.","label":"","id":"S09303"},"esterno":false,"offsetX":0,"offsetY":0,"nomeCitta":"A"},{"codReg":18,"tipoStazione":3,"dettZoomStaz":[],"pstaz":[],"mappaCitta":{"urlImagePinpoint":"","urlImageBaloon":""},"codiceStazione":"S09301","codStazione":"S09301","lat":41.03596,"lon":14.287658,"latMappaCitta":0.0,"lonMappaCitta":0.0,"localita":{"nomeLungo":"MARCIANISE","nomeBreve":"Marcianise","label":"","id":"S09301"},"esterno":false,"offsetX":0,"offsetY":0,"nomeCitta":"A"},{"codReg":18,"tipoStazione":3,"dettZoomStaz":[],"pstaz":[],"mappaCitta":{"urlImagePinpoint":"","urlImageBaloon":""},"codiceStazione":"S09750","codStazione":"S09750","lat":40.923733,"lon":14.460435,"latMappaCitta":0.0,"lonMappaCitta":0.0,"localita":{"nomeLungo":"MARIGLIANO","nomeBreve":"Marigliano","label":"","id":"S09750"},"esterno":false,"offsetX":0,"offsetY":0,"nomeCitta":"A"},{"codReg":18,"tipoStazione":3,"dettZoomStaz":[],"pstaz":[],"mappaCitta":{"urlImagePinpoint":"","urlImageBaloon":""},"codiceStazione":"S09201","codStazione":"S09201","lat":41.407585,"lon":13.986672,"latMappaCitta":0.0,"lonMappaCitta":0.0,"localita":{"nomeLungo":"MIGNANO DI MONTE LUNGO","nomeBreve":"Mignano Mont.","label":"","id":"S09201"},"esterno":false,"offsetX":0,"offsetY":0,"nomeCitta":"A"},{"codReg":18,"tipoStazione":3,"dettZoomStaz":[],"pstaz":[],"mappaCitta":{"urlImagePinpoint":"","urlImageBaloon":""},"codiceStazione":"S09824","codStazione":"S09824","lat":40.611057,"lon":15.052382,"latMappaCitta":0.0,"lonMappaCitta":0.0,"localita":{"nomeLungo":"EBOLI","nomeBreve":"Eboli","label":"","id":"S09824"},"esterno":false,"offsetX":0,"offsetY":0,"nomeCitta":"A"},{"codReg":18,"tipoStazione":3,"dettZoomStaz":[],"pstaz":[],"mappaCitta":{"urlImagePinpoint":"","urlImageBaloon":""},"codiceStazione":"S09520","codStazione":"S09520","lat":40.743779,"lon":14.77224,"latMappaCitta":0.0,"lonMappaCitta":0.0,"localita":{"nomeLungo":"BARONISSI","nomeBreve":"Baronissi","label":"","id":"S09520"},"esterno":false,"offsetX":0,"offsetY":0,"nomeCitta":"A"},{"codReg":18,"tipoStazione":3,"dettZoomStaz":[],"pstaz":[],"mappaCitta":{"urlImagePinpoint":"","urlImageBaloon":""},"codiceStazione":"S09503","codStazione":"S09503","lat":41.340445,"lon":14.677658,"latMappaCitta":0.0,"lonMappaCitta":0.0,"localita":{"nomeLungo":"MORCONE","nomeBreve":"Morcone","label":"","id":"S09503"},"esterno":false,"offsetX":0,"offsetY":0,"nomeCitta":"A"},{"codReg":18,"tipoStazione":3,"dettZoomStaz":[],"pstaz":[],"mappaCitta":{"urlImagePinpoint":"","urlImageBaloon":""},"codiceStazione":"S09103","codStazione":"S09103","lat":40.822462,"lon":14.194649,"latMappaCitta":0.0,"lonMappaCitta":0.0,"localita":{"nomeLungo":"NAPOLI CAMPI FLEGREI","nomeBreve":"Napoli Campi F.","label":"","id":"S09103"},"esterno":false,"offsetX":0,"offsetY":0,"nomeCitta":"A"},{"codReg":18,"tipoStazione":3,"dettZoomStaz":[],"pstaz":[],"mappaCitta":{"urlImagePinpoint":"","urlImageBaloon":""},"codiceStazione":"S09109","codStazione":"S09109","lat":40.852326,"lon":14.275159,"latMappaCitta":0.0,"lonMappaCitta":0.0,"localita":{"nomeLungo":"NAPOLI PIAZZA GARIBALDI","nomeBreve":"NA Piazza Garib.","label":"","id":"S09109"},"esterno":false,"offsetX":0,"offsetY":0,"nomeCitta":"A"},{"codReg":18,"tipoStazione":3,"dettZoomStaz":[],"pstaz":[],"mappaCitta":{"urlImagePinpoint":"","urlImageBaloon":""},"codiceStazione":"S09521","codStazione":"S09521","lat":40.719928,"lon":14.777354,"latMappaCitta":0.0,"lonMappaCitta":0.0,"localita":{"nomeLungo":"PELLEZZANO","nomeBreve":"Pellezzano","label":"","id":"S09521"},"esterno":false,"offsetX":0,"offsetY":0,"nomeCitta":"A"},{"codReg":18,"tipoStazione":4,"dettZoomStaz":[{"codiceStazione":"S09060","zoomStartRange":8,"zoomStopRange":9,"pinpointVisibile":true,"pinpointVisible":true,"labelVisibile":true,"labelVisible":true,"codiceRegione":null},{"codiceStazione":"S09060","zoomStartRange":10,"zoomStopRange":11,"pinpointVisibile":true,"pinpointVisible":true,"labelVisibile":true,"labelVisible":true,"codiceRegione":null}],"pstaz":[],"mappaCitta":{"urlImagePinpoint":"","urlImageBaloon":""},"codiceStazione":"S09060","codStazione":"S09060","lat":41.482975,"lon":14.048722,"latMappaCitta":0.0,"lonMappaCitta":0.0,"localita":{"nomeLungo":"VENAFRO","nomeBreve":"Venafro","label":"","id":"S09060"},"esterno":true,"offsetX":0,"offsetY":0,"nomeCitta":"Venafro"},{"codReg":18,"tipoStazione":3,"dettZoomStaz":[{"codiceStazione":"S09003","zoomStartRange":8,"zoomStopRange":9,"pinpointVisibile":true,"pinpointVisible":true,"labelVisibile":false,"labelVisible":false,"codiceRegione":null},{"codiceStazione":"S09003","zoomStartRange":10,"zoomStopRange":11,"pinpointVisibile":true,"pinpointVisible":true,"labelVisibile":true,"labelVisible":true,"codiceRegione":null}],"pstaz":[],"mappaCitta":{"urlImagePinpoint":"","urlImageBaloon":""},"codiceStazione":"S09003","codStazione":"S09003","lat":41.004956,"lon":14.06753,"latMappaCitta":0.0,"lonMappaCitta":0.0,"localita":{"nomeLungo":"VILLA LITERNO","nomeBreve":"Villa Literno","label":"","id":"S09003"},"esterno":false,"offsetX":90,"offsetY":0,"nomeCitta":"Villa Literno"},{"codReg":18,"tipoStazione":3,"dettZoomStaz":[],"pstaz":[],"mappaCitta":{"urlImagePinpoint":"","urlImageBaloon":""},"codiceStazione":"S09310","codStazione":"S09310","lat":41.163008,"lon":14.720027,"latMappaCitta":0.0,"lonMappaCitta":0.0,"localita":{"nomeLungo":"VITULANO FOGLIANISE","nomeBreve":"Vitulano Fogl.","label":"","id":"S09310"},"esterno":false,"offsetX":0,"offsetY":0,"nomeCitta":"A"},{"codReg":18,"tipoStazione":3,"dettZoomStaz":[],"pstaz":[],"mappaCitta":{"urlImagePinpoint":"","urlImageBaloon":""},"codiceStazione":"S09902","codStazione":"S09902","lat":40.534934,"lon":15.426706,"latMappaCitta":0.0,"lonMappaCitta":0.0,"localita":{"nomeLungo":"AULETTA","nomeBreve":"Auletta","label":"","id":"S09902"},"esterno":false,"offsetX":0,"offsetY":0,"nomeCitta":"A"},{"codReg":18,"tipoStazione":3,"dettZoomStaz":[],"pstaz":[],"mappaCitta":{"urlImagePinpoint":"","urlImageBaloon":""},"codiceStazione":"S09908","codStazione":"S09908","lat":40.335142,"lon":15.629921,"latMappaCitta":0.0,"lonMappaCitta":0.0,"localita":{"nomeLungo":"PADULA","nomeBreve":"Padula","label":"","id":"S09908"},"esterno":false,"offsetX":0,"offsetY":0,"nomeCitta":"A"},{"codReg":18,"tipoStazione":3,"dettZoomStaz":[],"pstaz":[],"mappaCitta":{"urlImagePinpoint":"","urlImageBaloon":""},"codiceStazione":"S09901","codStazione":"S09901","lat":40.560347,"lon":15.389298,"latMappaCitta":0.0,"lonMappaCitta":0.0,"localita":{"nomeLungo":"PETINA","nomeBreve":"Petina","label":"","id":"S09901"},"esterno":false,"offsetX":0,"offsetY":0,"nomeCitta":"A"},{"codReg":18,"tipoStazione":3,"dettZoomStaz":[],"pstaz":[],"mappaCitta":{"urlImagePinpoint":"","urlImageBaloon":""},"codiceStazione":"S09903","codStazione":"S09903","lat":40.512921,"lon":15.497238,"latMappaCitta":0.0,"lonMappaCitta":0.0,"localita":{"nomeLungo":"POLLA","nomeBreve":"Polla","label":"","id":"S09903"},"esterno":false,"offsetX":0,"offsetY":0,"nomeCitta":"A"},{"codReg":18,"tipoStazione":3,"dettZoomStaz":[],"pstaz":[],"mappaCitta":{"urlImagePinpoint":"","urlImageBaloon":""},"codiceStazione":"S09906","codStazione":"S09906","lat":40.405144,"lon":15.576057,"latMappaCitta":0.0,"lonMappaCitta":0.0,"localita":{"nomeLungo":"SALA CONSILINA","nomeBreve":"Sala Consilina","label":"","id":"S09906"},"esterno":false,"offsetX":0,"offsetY":0,"nomeCitta":"A"},{"codReg":18,"tipoStazione":3,"dettZoomStaz":[],"pstaz":[],"mappaCitta":{"urlImagePinpoint":"","urlImageBaloon":""},"codiceStazione":"S09810","codStazione":"S09810","lat":40.745918,"lon":14.501109,"latMappaCitta":0.0,"lonMappaCitta":0.0,"localita":{"nomeLungo":"POMPEI","nomeBreve":"Pompei","label":"","id":"S09810"},"esterno":false,"offsetX":0,"offsetY":0,"nomeCitta":"A"},{"codReg":18,"tipoStazione":3,"dettZoomStaz":[],"pstaz":[],"mappaCitta":{"urlImagePinpoint":"","urlImageBaloon":""},"codiceStazione":"S09504","codStazione":"S09504","lat":41.29578,"lon":14.712051,"latMappaCitta":0.0,"lonMappaCitta":0.0,"localita":{"nomeLungo":"PONTELANDOLFO","nomeBreve":"Pontelandolfo","label":"","id":"S09504"},"esterno":false,"offsetX":0,"offsetY":0,"nomeCitta":"A"},{"codReg":18,"tipoStazione":3,"dettZoomStaz":[],"pstaz":[],"mappaCitta":{"urlImagePinpoint":"","urlImageBaloon":""},"codiceStazione":"S09516","codStazione":"S09516","lat":40.834504,"lon":14.843975,"latMappaCitta":0.0,"lonMappaCitta":0.0,"localita":{"nomeLungo":"SOLOFRA","nomeBreve":"Solofra","label":"","id":"S09516"},"esterno":false,"offsetX":0,"offsetY":0,"nomeCitta":"A"},{"codReg":18,"tipoStazione":3,"dettZoomStaz":[],"pstaz":[],"mappaCitta":{"urlImagePinpoint":"","urlImageBaloon":""},"codiceStazione":"S09761","codStazione":"S09761","lat":40.891561,"lon":14.468487,"latMappaCitta":0.0,"lonMappaCitta":0.0,"localita":{"nomeLungo":"SPARTIMENTO DI SCISCIANO","nomeBreve":"S. di Scisciano","label":"","id":"S09761"},"esterno":false,"offsetX":0,"offsetY":0,"nomeCitta":"A"},{"codReg":18,"tipoStazione":3,"dettZoomStaz":[],"pstaz":[],"mappaCitta":{"urlImagePinpoint":"","urlImageBaloon":""},"codiceStazione":"S09308","codStazione":"S09308","lat":41.219748,"lon":14.648419,"latMappaCitta":0.0,"lonMappaCitta":0.0,"localita":{"nomeLungo":"S.LORENZO MAGGIORE","nomeBreve":"S.Lorenzo M.","label":"","id":"S09308"},"esterno":false,"offsetX":0,"offsetY":0,"nomeCitta":"A"},{"codReg":18,"tipoStazione":3,"dettZoomStaz":[{"codiceStazione":"S09005","zoomStartRange":8,"zoomStopRange":9,"pinpointVisibile":true,"pinpointVisible":true,"labelVisibile":false,"labelVisible":false,"codiceRegione":null},{"codiceStazione":"S09005","zoomStartRange":10,"zoomStopRange":11,"pinpointVisibile":true,"pinpointVisible":true,"labelVisibile":true,"labelVisible":true,"codiceRegione":null}],"pstaz":[],"mappaCitta":{"urlImagePinpoint":"","urlImageBaloon":""},"codiceStazione":"S09005","codStazione":"S09005","lat":40.992103,"lon":14.171976,"latMappaCitta":0.0,"lonMappaCitta":0.0,"localita":{"nomeLungo":"S.MARCELLINO FRIGNANO","nomeBreve":"S.Marcellino F.","label":"","id":"S09005"},"esterno":false,"offsetX":60,"offsetY":0,"nomeCitta":"S.Marcellino F."},{"codReg":18,"tipoStazione":3,"dettZoomStaz":[],"pstaz":[],"mappaCitta":{"urlImagePinpoint":"","urlImageBaloon":""},"codiceStazione":"S09209","codStazione":"S09209","lat":41.07353,"lon":14.254081,"latMappaCitta":0.0,"lonMappaCitta":0.0,"localita":{"nomeLungo":"S.MARIA CAPUA VETERE","nomeBreve":"S.Maria Capua V.","label":"","id":"S09209"},"esterno":false,"offsetX":0,"offsetY":0,"nomeCitta":"A"},{"codReg":18,"tipoStazione":3,"dettZoomStaz":[],"pstaz":[],"mappaCitta":{"urlImagePinpoint":"","urlImageBaloon":""},"codiceStazione":"S09804","codStazione":"S09804","lat":40.755435,"lon":14.407647,"latMappaCitta":0.0,"lonMappaCitta":0.0,"localita":{"nomeLungo":"S.MARIA LA BRUNA","nomeBreve":"S.Maria La Bruna","label":"","id":"S09804"},"esterno":false,"offsetX":0,"offsetY":0,"nomeCitta":"A"},{"codReg":18,"tipoStazione":3,"dettZoomStaz":[],"pstaz":[],"mappaCitta":{"urlImagePinpoint":"","urlImageBaloon":""},"codiceStazione":"S09753","codStazione":"S09753","lat":40.806926,"lon":14.503275,"latMappaCitta":0.0,"lonMappaCitta":0.0,"localita":{"nomeLungo":"TERZIGNO","nomeBreve":"Terzigno","label":"","id":"S09753"},"esterno":false,"offsetX":0,"offsetY":0,"nomeCitta":"A"},{"codReg":18,"tipoStazione":3,"dettZoomStaz":[],"pstaz":[],"mappaCitta":{"urlImagePinpoint":"","urlImageBaloon":""},"codiceStazione":"S09202","codStazione":"S09202","lat":41.358861,"lon":14.04514,"latMappaCitta":0.0,"lonMappaCitta":0.0,"localita":{"nomeLungo":"TORA PRESENZANO","nomeBreve":"Tora Presenzano","label":"","id":"S09202"},"esterno":false,"offsetX":0,"offsetY":0,"nomeCitta":"A"},{"codReg":18,"tipoStazione":3,"dettZoomStaz":[],"pstaz":[],"mappaCitta":{"urlImagePinpoint":"","urlImageBaloon":""},"codiceStazione":"S11705","codStazione":"S11705","lat":40.351521,"lon":15.002053,"latMappaCitta":0.0,"lonMappaCitta":0.0,"localita":{"nomeLungo":"AGROPOLI CASTELLABATE","nomeBreve":"Agropoli","label":"","id":"S11705"},"esterno":false,"offsetX":0,"offsetY":0,"nomeCitta":"A"},{"codReg":18,"tipoStazione":3,"dettZoomStaz":[],"pstaz":[],"mappaCitta":{"urlImagePinpoint":"","urlImageBaloon":""},"codiceStazione":"S11702","codStazione":"S11702","lat":40.454518,"lon":15.013551,"latMappaCitta":0.0,"lonMappaCitta":0.0,"localita":{"nomeLungo":"CAPACCIO ROCCADASPIDE","nomeBreve":"Capaccio","label":"","id":"S11702"},"esterno":false,"offsetX":0,"offsetY":0,"nomeCitta":"A"},{"codReg":18,"tipoStazione":3,"dettZoomStaz":[],"pstaz":[],"mappaCitta":{"urlImagePinpoint":"","urlImageBaloon":""},"codiceStazione":"S11712","codStazione":"S11712","lat":40.091539,"lon":15.243601,"latMappaCitta":0.0,"lonMappaCitta":0.0,"localita":{"nomeLungo":"PISCIOTTA PALINURO","nomeBreve":"Pisciotta P.","label":"","id":"S11712"},"esterno":false,"offsetX":0,"offsetY":0,"nomeCitta":"A"},{"codReg":18,"tipoStazione":3,"dettZoomStaz":[],"pstaz":[],"mappaCitta":{"urlImagePinpoint":"","urlImageBaloon":""},"codiceStazione":"S11717","codStazione":"S11717","lat":40.099017,"lon":15.481204,"latMappaCitta":0.0,"lonMappaCitta":0.0,"localita":{"nomeLungo":"TORRE ORSAIA","nomeBreve":"Torre Orsaia","label":"","id":"S11717"},"esterno":false,"offsetX":0,"offsetY":0,"nomeCitta":"A"},{"codReg":18,"tipoStazione":3,"dettZoomStaz":[],"pstaz":[],"mappaCitta":{"urlImagePinpoint":"","urlImageBaloon":""},"codiceStazione":"S09319","codStazione":"S09319","lat":41.235362,"lon":15.235132,"latMappaCitta":0.0,"lonMappaCitta":0.0,"localita":{"nomeLungo":"MONTAGUTO PANNI","nomeBreve":"Montaguto P.","label":"","id":"S09319"},"esterno":false,"offsetX":0,"offsetY":0,"nomeCitta":"A"},{"codReg":18,"tipoStazione":3,"dettZoomStaz":[],"pstaz":[],"mappaCitta":{"urlImagePinpoint":"","urlImageBaloon":""},"codiceStazione":"S09822","codStazione":"S09822","lat":40.617439,"lon":14.944628,"latMappaCitta":0.0,"lonMappaCitta":0.0,"localita":{"nomeLungo":"MONTECORVINO","nomeBreve":"Montecorvino","label":"","id":"S09822"},"esterno":false,"offsetX":0,"offsetY":0,"nomeCitta":"A"},{"codReg":18,"tipoStazione":3,"dettZoomStaz":[],"pstaz":[],"mappaCitta":{"urlImagePinpoint":"","urlImageBaloon":""},"codiceStazione":"S09614","codStazione":"S09614","lat":40.872272,"lon":15.095642,"latMappaCitta":0.0,"lonMappaCitta":0.0,"localita":{"nomeLungo":"NUSCO","nomeBreve":"Nusco","label":"","id":"S09614"},"esterno":false,"offsetX":0,"offsetY":0,"nomeCitta":"A"},{"codReg":18,"tipoStazione":3,"dettZoomStaz":[],"pstaz":[],"mappaCitta":{"urlImagePinpoint":"","urlImageBaloon":""},"codiceStazione":"S09001","codStazione":"S09001","lat":41.123525,"lon":13.971792,"latMappaCitta":0.0,"lonMappaCitta":0.0,"localita":{"nomeLungo":"FALCIANO MONDRAGONE CAR.","nomeBreve":"Falciano Mond.","label":"","id":"S09001"},"esterno":false,"offsetX":0,"offsetY":0,"nomeCitta":"A"},{"codReg":18,"tipoStazione":3,"dettZoomStaz":[],"pstaz":[],"mappaCitta":{"urlImagePinpoint":"","urlImageBaloon":""},"codiceStazione":"S09207","codStazione":"S09207","lat":41.17384,"lon":14.160545,"latMappaCitta":0.0,"lonMappaCitta":0.0,"localita":{"nomeLungo":"PIGNATARO MAGGIORE","nomeBreve":"Pignataro Mag.","label":"","id":"S09207"},"esterno":false,"offsetX":0,"offsetY":0,"nomeCitta":"A"},{"codReg":18,"tipoStazione":3,"dettZoomStaz":[],"pstaz":[],"mappaCitta":{"urlImagePinpoint":"","urlImageBaloon":""},"codiceStazione":"S09530","codStazione":"S09530","lat":41.136834,"lon":14.777662,"latMappaCitta":0.0,"lonMappaCitta":0.0,"localita":{"nomeLungo":"BENEVENTO ARCO TRAIANO","nomeBreve":"BN Arco Traiano","label":"","id":"S09530"},"esterno":false,"offsetX":0,"offsetY":0,"nomeCitta":"A"},{"codReg":18,"tipoStazione":3,"dettZoomStaz":[],"pstaz":[],"mappaCitta":{"urlImagePinpoint":"","urlImageBaloon":""},"codiceStazione":"S09606","codStazione":"S09606","lat":40.980381,"lon":14.994305,"latMappaCitta":0.0,"lonMappaCitta":0.0,"localita":{"nomeLungo":"LUOGOSANO","nomeBreve":"Luogosano","label":"","id":"S09606"},"esterno":false,"offsetX":0,"offsetY":0,"nomeCitta":"A"},{"codReg":18,"tipoStazione":3,"dettZoomStaz":[{"codiceStazione":"S09706","zoomStartRange":8,"zoomStopRange":9,"pinpointVisibile":true,"pinpointVisible":true,"labelVisibile":false,"labelVisible":false,"codiceRegione":null},{"codiceStazione":"S09706","zoomStartRange":10,"zoomStopRange":11,"pinpointVisibile":true,"pinpointVisible":true,"labelVisibile":true,"labelVisible":true,"codiceRegione":null}],"pstaz":[],"mappaCitta":{"urlImagePinpoint":"","urlImageBaloon":""},"codiceStazione":"S09706","codStazione":"S09706","lat":40.783095,"lon":14.759749,"latMappaCitta":0.0,"lonMappaCitta":0.0,"localita":{"nomeLungo":"MERCATO SAN SEVERINO","nomeBreve":"Mercato S.Sever.","label":"","id":"S09706"},"esterno":false,"offsetX":-4,"offsetY":10,"nomeCitta":"Mercato S.Sever."},{"codReg":18,"tipoStazione":3,"dettZoomStaz":[],"pstaz":[],"mappaCitta":{"urlImagePinpoint":"","urlImageBaloon":""},"codiceStazione":"S11714","codStazione":"S11714","lat":40.09683,"lon":15.298924,"latMappaCitta":0.0,"lonMappaCitta":0.0,"localita":{"nomeLungo":"SAN MAURO LA BRUCA","nomeBreve":"S.Mauro La Bruca","label":"","id":"S11714"},"esterno":false,"offsetX":0,"offsetY":0,"nomeCitta":"A"},{"codReg":18,"tipoStazione":3,"dettZoomStaz":[],"pstaz":[],"mappaCitta":{"urlImagePinpoint":"","urlImageBaloon":""},"codiceStazione":"S11700","codStazione":"S11700","lat":40.561479,"lon":14.998375,"latMappaCitta":0.0,"lonMappaCitta":0.0,"localita":{"nomeLungo":"SAN NICOLA VARCO DI EBOLI","nomeBreve":"S.Nicola Varco","label":"","id":"S11700"},"esterno":false,"offsetX":0,"offsetY":0,"nomeCitta":"A"},{"codReg":18,"tipoStazione":3,"dettZoomStaz":[{"codiceStazione":"S11721","zoomStartRange":8,"zoomStopRange":9,"pinpointVisibile":true,"pinpointVisible":true,"labelVisibile":false,"labelVisible":false,"codiceRegione":null},{"codiceStazione":"S11721","zoomStartRange":10,"zoomStopRange":11,"pinpointVisibile":true,"pinpointVisible":true,"labelVisibile":true,"labelVisible":true,"codiceRegione":null}],"pstaz":[],"mappaCitta":{"urlImagePinpoint":"","urlImageBaloon":""},"codiceStazione":"S11721","codStazione":"S11721","lat":40.078013,"lon":15.627204,"latMappaCitta":0.0,"lonMappaCitta":0.0,"localita":{"nomeLungo":"SAPRI","nomeBreve":"Sapri","label":"","id":"S11721"},"esterno":false,"offsetX":20,"offsetY":0,"nomeCitta":"Sapri"},{"codReg":18,"tipoStazione":3,"dettZoomStaz":[],"pstaz":[],"mappaCitta":{"urlImagePinpoint":"","urlImageBaloon":""},"codiceStazione":"S09215","codStazione":"S09215","lat":40.939066,"lon":14.372243,"latMappaCitta":0.0,"lonMappaCitta":0.0,"localita":{"nomeLungo":"ACERRA","nomeBreve":"Acerra","label":"","id":"S09215"},"esterno":false,"offsetX":0,"offsetY":0,"nomeCitta":"A"},{"codReg":18,"tipoStazione":3,"dettZoomStaz":[],"pstaz":[],"mappaCitta":{"urlImagePinpoint":"","urlImageBaloon":""},"codiceStazione":"S09812","codStazione":"S09812","lat":40.746404,"lon":14.575366,"latMappaCitta":0.0,"lonMappaCitta":0.0,"localita":{"nomeLungo":"ANGRI","nomeBreve":"Angri","label":"","id":"S09812"},"esterno":false,"offsetX":0,"offsetY":0,"nomeCitta":"A"},{"codReg":18,"tipoStazione":3,"dettZoomStaz":[{"codiceStazione":"S09314","zoomStartRange":8,"zoomStopRange":9,"pinpointVisibile":true,"pinpointVisible":true,"labelVisibile":false,"labelVisible":false,"codiceRegione":null},{"codiceStazione":"S09314","zoomStartRange":10,"zoomStopRange":11,"pinpointVisibile":true,"pinpointVisible":true,"labelVisibile":true,"labelVisible":true,"codiceRegione":null}],"pstaz":[],"mappaCitta":{"urlImagePinpoint":"","urlImageBaloon":""},"codiceStazione":"S09314","codStazione":"S09314","lat":41.140927,"lon":14.918733,"latMappaCitta":0.0,"lonMappaCitta":0.0,"localita":{"nomeLungo":"APICE S.ARCANGELO BONITO","nomeBreve":"Apice S.A.B.","label":"","id":"S09314"},"esterno":false,"offsetX":-4,"offsetY":18,"nomeCitta":"Apice S.A.B."},{"codReg":18,"tipoStazione":3,"dettZoomStaz":[],"pstaz":[],"mappaCitta":{"urlImagePinpoint":"","urlImageBaloon":""},"codiceStazione":"S09623","codStazione":"S09623","lat":40.940252,"lon":15.541249,"latMappaCitta":0.0,"lonMappaCitta":0.0,"localita":{"nomeLungo":"AQUILONIA","nomeBreve":"Aquilonia","label":"","id":"S09623"},"esterno":false,"offsetX":0,"offsetY":0,"nomeCitta":"A"},{"codReg":18,"tipoStazione":3,"dettZoomStaz":[],"pstaz":[],"mappaCitta":{"urlImagePinpoint":"","urlImageBaloon":""},"codiceStazione":"S09316","codStazione":"S09316","lat":41.181883,"lon":15.117508,"latMappaCitta":0.0,"lonMappaCitta":0.0,"localita":{"nomeLungo":"ARIANO IRPINO","nomeBreve":"Ariano Irpino","label":"","id":"S09316"},"esterno":false,"offsetX":0,"offsetY":0,"nomeCitta":"A"},{"codReg":18,"tipoStazione":3,"dettZoomStaz":[{"codiceStazione":"S09514","zoomStartRange":8,"zoomStopRange":9,"pinpointVisibile":true,"pinpointVisible":true,"labelVisibile":true,"labelVisible":true,"codiceRegione":null},{"codiceStazione":"S09514","zoomStartRange":10,"zoomStopRange":11,"pinpointVisibile":true,"pinpointVisible":true,"labelVisibile":true,"labelVisible":true,"codiceRegione":null}],"pstaz":[],"mappaCitta":{"urlImagePinpoint":"","urlImageBaloon":""},"codiceStazione":"S09514","codStazione":"S09514","lat":40.921612,"lon":14.820586,"latMappaCitta":0.0,"lonMappaCitta":0.0,"localita":{"nomeLungo":"AVELLINO","nomeBreve":"Avellino","label":"Avellino","id":"S09514"},"esterno":false,"offsetX":-4,"offsetY":18,"nomeCitta":"Avellino"},{"codReg":18,"tipoStazione":3,"dettZoomStaz":[{"codiceStazione":"S09006","zoomStartRange":8,"zoomStopRange":9,"pinpointVisibile":true,"pinpointVisible":true,"labelVisibile":false,"labelVisible":false,"codiceRegione":null},{"codiceStazione":"S09006","zoomStartRange":10,"zoomStopRange":11,"pinpointVisibile":true,"pinpointVisible":true,"labelVisibile":true,"labelVisible":true,"codiceRegione":null}],"pstaz":[],"mappaCitta":{"urlImagePinpoint":"","urlImageBaloon":""},"codiceStazione":"S09006","codStazione":"S09006","lat":40.973323,"lon":14.218578,"latMappaCitta":0.0,"lonMappaCitta":0.0,"localita":{"nomeLungo":"AVERSA","nomeBreve":"Aversa","label":"","id":"S09006"},"esterno":false,"offsetX":0,"offsetY":0,"nomeCitta":"Aversa"},{"codReg":18,"tipoStazione":3,"dettZoomStaz":[],"pstaz":[],"mappaCitta":{"urlImagePinpoint":"","urlImageBaloon":""},"codiceStazione":"S09763","codStazione":"S09763","lat":40.732794,"lon":14.471878,"latMappaCitta":0.0,"lonMappaCitta":0.0,"localita":{"nomeLungo":"BOCCIA AL MAURO","nomeBreve":"Boccia al Mauro","label":"","id":"S09763"},"esterno":false,"offsetX":0,"offsetY":0,"nomeCitta":"A"},{"codReg":18,"tipoStazione":3,"dettZoomStaz":[],"pstaz":[],"mappaCitta":{"urlImagePinpoint":"","urlImageBaloon":""},"codiceStazione":"S09526","codStazione":"S09526","lat":40.845976,"lon":14.784092,"latMappaCitta":0.0,"lonMappaCitta":0.0,"localita":{"nomeLungo":"BORGO","nomeBreve":"Borgo","label":"","id":"S09526"},"esterno":false,"offsetX":0,"offsetY":0,"nomeCitta":"A"},{"codReg":18,"tipoStazione":3,"dettZoomStaz":[],"pstaz":[],"mappaCitta":{"urlImagePinpoint":"","urlImageBaloon":""},"codiceStazione":"S09754","codStazione":"S09754","lat":40.770786,"lon":14.48017,"latMappaCitta":0.0,"lonMappaCitta":0.0,"localita":{"nomeLungo":"BOSCOREALE","nomeBreve":"Boscoreale","label":"","id":"S09754"},"esterno":false,"offsetX":0,"offsetY":0,"nomeCitta":"A"},{"codReg":18,"tipoStazione":3,"dettZoomStaz":[{"codiceStazione":"S09213","zoomStartRange":8,"zoomStopRange":9,"pinpointVisibile":true,"pinpointVisible":true,"labelVisibile":false,"labelVisible":false,"codiceRegione":null},{"codiceStazione":"S09213","zoomStartRange":10,"zoomStopRange":11,"pinpointVisibile":true,"pinpointVisible":true,"labelVisibile":true,"labelVisible":true,"codiceRegione":null}],"pstaz":[],"mappaCitta":{"urlImagePinpoint":"","urlImageBaloon":""},"codiceStazione":"S09213","codStazione":"S09213","lat":40.993063,"lon":14.418877,"latMappaCitta":0.0,"lonMappaCitta":0.0,"localita":{"nomeLungo":"CANCELLO","nomeBreve":"Cancello","label":"","id":"S09213"},"esterno":false,"offsetX":-4,"offsetY":18,"nomeCitta":"Cancello"},{"codReg":18,"tipoStazione":3,"dettZoomStaz":[],"pstaz":[],"mappaCitta":{"urlImagePinpoint":"","urlImageBaloon":""},"codiceStazione":"S09002","codStazione":"S09002","lat":41.063369,"lon":14.02901,"latMappaCitta":0.0,"lonMappaCitta":0.0,"localita":{"nomeLungo":"CANCELLO ARNONE","nomeBreve":"Cancello Arnone","label":"","id":"S09002"},"esterno":false,"offsetX":0,"offsetY":0,"nomeCitta":"A"},{"codReg":18,"tipoStazione":3,"dettZoomStaz":[],"pstaz":[],"mappaCitta":{"urlImagePinpoint":"","urlImageBaloon":""},"codiceStazione":"S09208","codStazione":"S09208","lat":41.101306,"lon":14.210347,"latMappaCitta":0.0,"lonMappaCitta":0.0,"localita":{"nomeLungo":"CAPUA","nomeBreve":"Capua","label":"","id":"S09208"},"esterno":false,"offsetX":0,"offsetY":0,"nomeCitta":"A"},{"codReg":18,"tipoStazione":3,"dettZoomStaz":[],"pstaz":[],"mappaCitta":{"urlImagePinpoint":"","urlImageBaloon":""},"codiceStazione":"S09910","codStazione":"S09910","lat":40.214093,"lon":15.686095,"latMappaCitta":0.0,"lonMappaCitta":0.0,"localita":{"nomeLungo":"CASALBUONO","nomeBreve":"Casalbuono","label":"","id":"S09910"},"esterno":false,"offsetX":0,"offsetY":0,"nomeCitta":"A"},{"codReg":18,"tipoStazione":3,"dettZoomStaz":[{"codiceStazione":"S09211","zoomStartRange":8,"zoomStopRange":9,"pinpointVisibile":true,"pinpointVisible":true,"labelVisibile":true,"labelVisible":true,"codiceRegione":null},{"codiceStazione":"S09211","zoomStartRange":10,"zoomStopRange":11,"pinpointVisibile":true,"pinpointVisible":true,"labelVisibile":true,"labelVisible":true,"codiceRegione":null}],"pstaz":[],"mappaCitta":{"urlImagePinpoint":"","urlImageBaloon":""},"codiceStazione":"S09211","codStazione":"S09211","lat":41.068655,"lon":14.328457,"latMappaCitta":0.0,"lonMappaCitta":0.0,"localita":{"nomeLungo":"CASERTA","nomeBreve":"Caserta","label":"Caserta","id":"S09211"},"esterno":false,"offsetX":53,"offsetY":20,"nomeCitta":"Caserta"},{"codReg":18,"tipoStazione":3,"dettZoomStaz":[],"pstaz":[],"mappaCitta":{"urlImagePinpoint":"","urlImageBaloon":""},"codiceStazione":"S09009","codStazione":"S09009","lat":40.907762,"lon":14.29874,"latMappaCitta":0.0,"lonMappaCitta":0.0,"localita":{"nomeLungo":"CASORIA","nomeBreve":"Casoria","label":"","id":"S09009"},"esterno":false,"offsetX":0,"offsetY":0,"nomeCitta":"A"},{"codReg":18,"tipoStazione":3,"dettZoomStaz":[],"pstaz":[],"mappaCitta":{"urlImagePinpoint":"","urlImageBaloon":""},"codiceStazione":"S09611","codStazione":"S09611","lat":40.869227,"lon":15.031213,"latMappaCitta":0.0,"lonMappaCitta":0.0,"localita":{"nomeLungo":"CASSANO IRPINO","nomeBreve":"Cassano Irpino","label":"","id":"S09611"},"esterno":false,"offsetX":0,"offsetY":0,"nomeCitta":"A"},{"codReg":18,"tipoStazione":3,"dettZoomStaz":[],"pstaz":[],"mappaCitta":{"urlImagePinpoint":"","urlImageBaloon":""},"codiceStazione":"S09609","codStazione":"S09609","lat":40.935968,"lon":15.038655,"latMappaCitta":0.0,"lonMappaCitta":0.0,"localita":{"nomeLungo":"CASTELFRANCI","nomeBreve":"Castelfranci","label":"","id":"S09609"},"esterno":false,"offsetX":0,"offsetY":0,"nomeCitta":"A"},{"codReg":18,"tipoStazione":3,"dettZoomStaz":[],"pstaz":[],"mappaCitta":{"urlImagePinpoint":"","urlImageBaloon":""},"codiceStazione":"S09756","codStazione":"S09756","lat":40.701398,"lon":14.483737,"latMappaCitta":0.0,"lonMappaCitta":0.0,"localita":{"nomeLungo":"CASTELLAMMARE DI STABIA","nomeBreve":"Cast.re di Stab.","label":"","id":"S09756"},"esterno":false,"offsetX":0,"offsetY":0,"nomeCitta":"A"},{"codReg":18,"tipoStazione":3,"dettZoomStaz":[{"codiceStazione":"S09816","zoomStartRange":8,"zoomStopRange":9,"pinpointVisibile":true,"pinpointVisible":true,"labelVisibile":false,"labelVisible":false,"codiceRegione":null},{"codiceStazione":"S09816","zoomStartRange":10,"zoomStopRange":11,"pinpointVisibile":true,"pinpointVisible":true,"labelVisibile":true,"labelVisible":true,"codiceRegione":null}],"pstaz":[],"mappaCitta":{"urlImagePinpoint":"","urlImageBaloon":""},"codiceStazione":"S09816","codStazione":"S09816","lat":40.703662,"lon":14.708461,"latMappaCitta":0.0,"lonMappaCitta":0.0,"localita":{"nomeLungo":"CAVA DEI TIRRENI","nomeBreve":"Cava Dei Tirreni","label":"","id":"S09816"},"esterno":false,"offsetX":35,"offsetY":0,"nomeCitta":"Cava dei Tirreni"},{"codReg":18,"tipoStazione":3,"dettZoomStaz":[],"pstaz":[],"mappaCitta":{"urlImagePinpoint":"","urlImageBaloon":""},"codiceStazione":"S09113","codStazione":"S09113","lat":40.819292,"lon":14.185679,"latMappaCitta":0.0,"lonMappaCitta":0.0,"localita":{"nomeLungo":"CAVALLEGGERI AOSTA","nomeBreve":"Cavalleggeri A.","label":"","id":"S09113"},"esterno":false,"offsetX":0,"offsetY":0,"nomeCitta":"A"},{"codReg":18,"tipoStazione":3,"dettZoomStaz":[],"pstaz":[],"mappaCitta":{"urlImagePinpoint":"","urlImageBaloon":""},"codiceStazione":"S11711","codStazione":"S11711","lat":40.140955,"lon":15.172626,"latMappaCitta":0.0,"lonMappaCitta":0.0,"localita":{"nomeLungo":"ASCEA","nomeBreve":"Ascea","label":"","id":"S11711"},"esterno":false,"offsetX":0,"offsetY":0,"nomeCitta":"A"},{"codReg":18,"tipoStazione":3,"dettZoomStaz":[{"codiceStazione":"S09823","zoomStartRange":8,"zoomStopRange":9,"pinpointVisibile":true,"pinpointVisible":true,"labelVisibile":false,"labelVisible":false,"codiceRegione":null},{"codiceStazione":"S09823","zoomStartRange":10,"zoomStopRange":11,"pinpointVisibile":true,"pinpointVisible":true,"labelVisibile":true,"labelVisible":true,"codiceRegione":null}],"pstaz":[],"mappaCitta":{"urlImagePinpoint":"","urlImageBaloon":""},"codiceStazione":"S09823","codStazione":"S09823","lat":40.605789,"lon":14.98324,"latMappaCitta":0.0,"lonMappaCitta":0.0,"localita":{"nomeLungo":"BATTIPAGLIA","nomeBreve":"Battipaglia","label":"","id":"S09823"},"esterno":false,"offsetX":60,"offsetY":0,"nomeCitta":"Battipaglia"},{"codReg":18,"tipoStazione":3,"dettZoomStaz":[],"pstaz":[],"mappaCitta":{"urlImagePinpoint":"","urlImageBaloon":""},"codiceStazione":"S11716","codStazione":"S11716","lat":40.10287,"lon":15.39473,"latMappaCitta":0.0,"lonMappaCitta":0.0,"localita":{"nomeLungo":"CELLE BULGHERIA ROCCAGLORIOSA","nomeBreve":"Celle Bulgheria","label":"","id":"S11716"},"esterno":false,"offsetX":0,"offsetY":0,"nomeCitta":"A"},{"codReg":18,"tipoStazione":3,"dettZoomStaz":[],"pstaz":[],"mappaCitta":{"urlImagePinpoint":"","urlImageBaloon":""},"codiceStazione":"S11715","codStazione":"S11715","lat":40.090672,"lon":15.34674,"latMappaCitta":0.0,"lonMappaCitta":0.0,"localita":{"nomeLungo":"CENTOLA","nomeBreve":"Centola","label":"","id":"S11715"},"esterno":false,"offsetX":0,"offsetY":0,"nomeCitta":"A"},{"codReg":18,"tipoStazione":3,"dettZoomStaz":[],"pstaz":[],"mappaCitta":{"urlImagePinpoint":"","urlImageBaloon":""},"codiceStazione":"S11708","codStazione":"S11708","lat":40.252688,"lon":15.134406,"latMappaCitta":0.0,"lonMappaCitta":0.0,"localita":{"nomeLungo":"OMIGNANO SALENTO","nomeBreve":"Omignano","label":"","id":"S11708"},"esterno":false,"offsetX":0,"offsetY":0,"nomeCitta":"A"},{"codReg":18,"tipoStazione":3,"dettZoomStaz":[],"pstaz":[],"mappaCitta":{"urlImagePinpoint":"","urlImageBaloon":""},"codiceStazione":"S11718","codStazione":"S11718","lat":40.076482,"lon":15.528438,"latMappaCitta":0.0,"lonMappaCitta":0.0,"localita":{"nomeLungo":"POLICASTRO BUSSENTINO","nomeBreve":"Policastro","label":"","id":"S11718"},"esterno":false,"offsetX":0,"offsetY":0,"nomeCitta":"A"},{"codReg":18,"tipoStazione":3,"dettZoomStaz":[],"pstaz":[],"mappaCitta":{"urlImagePinpoint":"","urlImageBaloon":""},"codiceStazione":"S09473","codStazione":"S09473","lat":41.210883,"lon":14.787329,"latMappaCitta":0.0,"lonMappaCitta":0.0,"localita":{"nomeLungo":"CESE","nomeBreve":"Cese","label":"","id":"S09473"},"esterno":false,"offsetX":0,"offsetY":0,"nomeCitta":"A"},{"codReg":18,"tipoStazione":3,"dettZoomStaz":[],"pstaz":[],"mappaCitta":{"urlImagePinpoint":"","urlImageBaloon":""},"codiceStazione":"S09510","codStazione":"S09510","lat":41.050122,"lon":14.777618,"latMappaCitta":0.0,"lonMappaCitta":0.0,"localita":{"nomeLungo":"CHIANCHE CEPPALONI","nomeBreve":"Chianche Ceppal.","label":"","id":"S09510"},"esterno":false,"offsetX":0,"offsetY":0,"nomeCitta":"A"},{"codReg":18,"tipoStazione":3,"dettZoomStaz":[{"codiceStazione":"S09703","zoomStartRange":8,"zoomStopRange":9,"pinpointVisibile":true,"pinpointVisible":true,"labelVisibile":false,"labelVisible":false,"codiceRegione":null},{"codiceStazione":"S09703","zoomStartRange":10,"zoomStopRange":11,"pinpointVisibile":true,"pinpointVisible":true,"labelVisibile":true,"labelVisible":true,"codiceRegione":null}],"pstaz":[],"mappaCitta":{"urlImagePinpoint":"","urlImageBaloon":""},"codiceStazione":"S09703","codStazione":"S09703","lat":40.767687,"lon":14.665622,"latMappaCitta":0.0,"lonMappaCitta":0.0,"localita":{"nomeLungo":"CODOLA","nomeBreve":"Codola","label":"","id":"S09703"},"esterno":false,"offsetX":20,"offsetY":18,"nomeCitta":"Codola"},{"codReg":18,"tipoStazione":3,"dettZoomStaz":[],"pstaz":[],"mappaCitta":{"urlImagePinpoint":"","urlImageBaloon":""},"codiceStazione":"S09318","codStazione":"S09318","lat":41.230587,"lon":15.167109,"latMappaCitta":0.0,"lonMappaCitta":0.0,"localita":{"nomeLungo":"SAVIGNANO GRECI","nomeBreve":"Savignano G.","label":"","id":"S09318"},"esterno":false,"offsetX":0,"offsetY":0,"nomeCitta":"A"},{"codReg":18,"tipoStazione":3,"dettZoomStaz":[],"pstaz":[],"mappaCitta":{"urlImagePinpoint":"","urlImageBaloon":""},"codiceStazione":"S09811","codStazione":"S09811","lat":40.746028,"lon":14.523253,"latMappaCitta":0.0,"lonMappaCitta":0.0,"localita":{"nomeLungo":"SCAFATI","nomeBreve":"Scafati","label":"","id":"S09811"},"esterno":false,"offsetX":0,"offsetY":0,"nomeCitta":"A"},{"codReg":18,"tipoStazione":3,"dettZoomStaz":[],"pstaz":[],"mappaCitta":{"urlImagePinpoint":"","urlImageBaloon":""},"codiceStazione":"S09000","codStazione":"S09000","lat":41.1955,"lon":13.8761,"latMappaCitta":0.0,"lonMappaCitta":0.0,"localita":{"nomeLungo":"SESSA AURUNCA R.","nomeBreve":"Sessa A.","label":"","id":"S09000"},"esterno":false,"offsetX":0,"offsetY":0,"nomeCitta":"A"},{"codReg":18,"tipoStazione":3,"dettZoomStaz":[],"pstaz":[],"mappaCitta":{"urlImagePinpoint":"","urlImageBaloon":""},"codiceStazione":"S09307","codStazione":"S09307","lat":41.210521,"lon":14.571413,"latMappaCitta":0.0,"lonMappaCitta":0.0,"localita":{"nomeLungo":"SOLOPACA","nomeBreve":"Solopaca","label":"","id":"S09307"},"esterno":false,"offsetX":0,"offsetY":0,"nomeCitta":"A"},{"codReg":18,"tipoStazione":3,"dettZoomStaz":[],"pstaz":[],"mappaCitta":{"urlImagePinpoint":"","urlImageBaloon":""},"codiceStazione":"S09205","codStazione":"S09205","lat":41.231804,"lon":14.077075,"latMappaCitta":0.0,"lonMappaCitta":0.0,"localita":{"nomeLungo":"TEANO","nomeBreve":"Teano","label":"","id":"S09205"},"esterno":false,"offsetX":0,"offsetY":0,"nomeCitta":"A"},{"codReg":18,"tipoStazione":3,"dettZoomStaz":[],"pstaz":[],"mappaCitta":{"urlImagePinpoint":"","urlImageBaloon":""},"codiceStazione":"S09519","codStazione":"S09519","lat":40.759095,"lon":14.77486,"latMappaCitta":0.0,"lonMappaCitta":0.0,"localita":{"nomeLungo":"FISCIANO","nomeBreve":"Fisciano","label":"","id":"S09519"},"esterno":false,"offsetX":0,"offsetY":0,"nomeCitta":"A"},{"codReg":18,"tipoStazione":4,"dettZoomStaz":[{"codiceStazione":"S08640","zoomStartRange":8,"zoomStopRange":9,"pinpointVisibile":true,"pinpointVisible":true,"labelVisibile":true,"labelVisible":true,"codiceRegione":null},{"codiceStazione":"S08640","zoomStartRange":10,"zoomStopRange":11,"pinpointVisibile":true,"pinpointVisible":true,"labelVisibile":true,"labelVisible":true,"codiceRegione":null}],"pstaz":[],"mappaCitta":{"urlImagePinpoint":"","urlImageBaloon":""},"codiceStazione":"S08640","codStazione":"S08640","lat":41.258773,"lon":13.605996,"latMappaCitta":0.0,"lonMappaCitta":0.0,"localita":{"nomeLungo":"FORMIA-GAETA","nomeBreve":"Formia-Gaeta","label":"","id":"S08640"},"esterno":true,"offsetX":-4,"offsetY":18,"nomeCitta":"Formia-Gaeta"},{"codReg":18,"tipoStazione":3,"dettZoomStaz":[],"pstaz":[],"mappaCitta":{"urlImagePinpoint":"","urlImageBaloon":""},"codiceStazione":"S09607","codStazione":"S09607","lat":40.972903,"lon":15.009932,"latMappaCitta":0.0,"lonMappaCitta":0.0,"localita":{"nomeLungo":"PATERNOPOLI","nomeBreve":"Paternopoli","label":"","id":"S09607"},"esterno":false,"offsetX":0,"offsetY":0,"nomeCitta":"A"},{"codReg":18,"tipoStazione":3,"dettZoomStaz":[],"pstaz":[],"mappaCitta":{"urlImagePinpoint":"","urlImageBaloon":""},"codiceStazione":"S09324","codStazione":"S09324","lat":41.164472,"lon":14.958463,"latMappaCitta":0.0,"lonMappaCitta":0.0,"localita":{"nomeLungo":"CORSANO","nomeBreve":"Corsano","label":"","id":"S09324"},"esterno":false,"offsetX":0,"offsetY":0,"nomeCitta":"A"},{"codReg":18,"tipoStazione":3,"dettZoomStaz":[{"codiceStazione":"S09758","zoomStartRange":8,"zoomStopRange":9,"pinpointVisibile":true,"pinpointVisible":true,"labelVisibile":false,"labelVisible":false,"codiceRegione":null},{"codiceStazione":"S09758","zoomStartRange":10,"zoomStopRange":11,"pinpointVisibile":true,"pinpointVisible":true,"labelVisibile":true,"labelVisible":true,"codiceRegione":null}],"pstaz":[],"mappaCitta":{"urlImagePinpoint":"","urlImageBaloon":""},"codiceStazione":"S09758","codStazione":"S09758","lat":40.688964,"lon":14.520445,"latMappaCitta":0.0,"lonMappaCitta":0.0,"localita":{"nomeLungo":"GRAGNANO","nomeBreve":"Gragnano","label":"","id":"S09758"},"esterno":false,"offsetX":55,"offsetY":0,"nomeCitta":"Gragnano"},{"codReg":18,"tipoStazione":3,"dettZoomStaz":[],"pstaz":[],"mappaCitta":{"urlImagePinpoint":"","urlImageBaloon":""},"codiceStazione":"S09707","codStazione":"S09707","lat":40.769685,"lon":14.68115,"latMappaCitta":0.0,"lonMappaCitta":0.0,"localita":{"nomeLungo":"LANZARA FIMIANI","nomeBreve":"Lanzara Fimiani","label":"","id":"S09707"},"esterno":false,"offsetX":0,"offsetY":0,"nomeCitta":"A"},{"codReg":18,"tipoStazione":3,"dettZoomStaz":[],"pstaz":[],"mappaCitta":{"urlImagePinpoint":"","urlImageBaloon":""},"codiceStazione":"S09708","codStazione":"S09708","lat":40.78733,"lon":14.649875,"latMappaCitta":0.0,"lonMappaCitta":0.0,"localita":{"nomeLungo":"LAVORATE","nomeBreve":"Lavorate","label":"","id":"S09708"},"esterno":false,"offsetX":0,"offsetY":0,"nomeCitta":"A"},{"codReg":18,"tipoStazione":3,"dettZoomStaz":[],"pstaz":[],"mappaCitta":{"urlImagePinpoint":"","urlImageBaloon":""},"codiceStazione":"S09613","codStazione":"S09613","lat":40.83917,"lon":15.06324,"latMappaCitta":0.0,"lonMappaCitta":0.0,"localita":{"nomeLungo":"BAGNOLI IRPINO","nomeBreve":"Bagnoli Irpino","label":"","id":"S09613"},"esterno":false,"offsetX":0,"offsetY":0,"nomeCitta":"A"},{"codReg":18,"tipoStazione":1,"dettZoomStaz":[{"codiceStazione":"S09818","zoomStartRange":8,"zoomStopRange":9,"pinpointVisibile":true,"pinpointVisible":true,"labelVisibile":true,"labelVisible":true,"codiceRegione":null},{"codiceStazione":"S09818","zoomStartRange":10,"zoomStopRange":11,"pinpointVisibile":true,"pinpointVisible":true,"labelVisibile":true,"labelVisible":true,"codiceRegione":null}],"pstaz":[],"mappaCitta":{"urlImagePinpoint":"","urlImageBaloon":""},"codiceStazione":"S09818","codStazione":"S09818","lat":40.675137,"lon":14.772822,"latMappaCitta":0.0,"lonMappaCitta":0.0,"localita":{"nomeLungo":"SALERNO","nomeBreve":"Salerno","label":"Salerno","id":"S09818"},"esterno":false,"offsetX":-4,"offsetY":10,"nomeCitta":"Salerno"},{"codReg":18,"tipoStazione":3,"dettZoomStaz":[],"pstaz":[],"mappaCitta":{"urlImagePinpoint":"","urlImageBaloon":""},"codiceStazione":"S09600","codStazione":"S09600","lat":40.922251,"lon":14.881761,"latMappaCitta":0.0,"lonMappaCitta":0.0,"localita":{"nomeLungo":"SALZA IRPINA","nomeBreve":"Salza Irpina","label":"","id":"S09600"},"esterno":false,"offsetX":0,"offsetY":0,"nomeCitta":"A"},{"codReg":18,"tipoStazione":3,"dettZoomStaz":[{"codiceStazione":"S09702","zoomStartRange":8,"zoomStopRange":9,"pinpointVisibile":true,"pinpointVisible":true,"labelVisibile":false,"labelVisible":false,"codiceRegione":null},{"codiceStazione":"S09702","zoomStartRange":10,"zoomStopRange":11,"pinpointVisibile":true,"pinpointVisible":true,"labelVisibile":true,"labelVisible":true,"codiceRegione":null}],"pstaz":[],"mappaCitta":{"urlImagePinpoint":"","urlImageBaloon":""},"codiceStazione":"S09702","codStazione":"S09702","lat":40.813063,"lon":14.612442,"latMappaCitta":0.0,"lonMappaCitta":0.0,"localita":{"nomeLungo":"SARNO","nomeBreve":"Sarno","label":"","id":"S09702"},"esterno":false,"offsetX":35,"offsetY":0,"nomeCitta":"Sarno"},{"codReg":18,"tipoStazione":3,"dettZoomStaz":[],"pstaz":[],"mappaCitta":{"urlImagePinpoint":"","urlImageBaloon":""},"codiceStazione":"S09518","codStazione":"S09518","lat":40.819987,"lon":14.757381,"latMappaCitta":0.0,"lonMappaCitta":0.0,"localita":{"nomeLungo":"MONTORO FORINO","nomeBreve":"Montoro Forino","label":"","id":"S09518"},"esterno":false,"offsetX":0,"offsetY":0,"nomeCitta":"A"},{"codReg":18,"tipoStazione":3,"dettZoomStaz":[],"pstaz":[],"mappaCitta":{"urlImagePinpoint":"","urlImageBaloon":""},"codiceStazione":"S09517","codStazione":"S09517","lat":40.831616,"lon":14.80217,"latMappaCitta":0.0,"lonMappaCitta":0.0,"localita":{"nomeLungo":"MONTORO SUPERIORE","nomeBreve":"Montoro Super.","label":"","id":"S09517"},"esterno":false,"offsetX":0,"offsetY":0,"nomeCitta":"A"},{"codReg":18,"tipoStazione":3,"dettZoomStaz":[],"pstaz":[],"mappaCitta":{"urlImagePinpoint":"","urlImageBaloon":""},"codiceStazione":"S09528","codStazione":"S09528","lat":41.080487,"lon":14.786519,"latMappaCitta":0.0,"lonMappaCitta":0.0,"localita":{"nomeLungo":"MONTORSI","nomeBreve":"Montorsi","label":"","id":"S09528"},"esterno":false,"offsetX":0,"offsetY":0,"nomeCitta":"A"},{"codReg":18,"tipoStazione":3,"dettZoomStaz":[],"pstaz":[],"mappaCitta":{"urlImagePinpoint":"","urlImageBaloon":""},"codiceStazione":"S09110","codStazione":"S09110","lat":40.853959,"lon":14.288213,"latMappaCitta":0.0,"lonMappaCitta":0.0,"localita":{"nomeLungo":"NAPOLI GIANTURCO","nomeBreve":"Napoli Gianturco","label":"","id":"S09110"},"esterno":false,"offsetX":0,"offsetY":0,"nomeCitta":"A"},{"codReg":18,"tipoStazione":3,"dettZoomStaz":[],"pstaz":[],"mappaCitta":{"urlImagePinpoint":"","urlImageBaloon":""},"codiceStazione":"S09105","codStazione":"S09105","lat":40.831531,"lon":14.218662,"latMappaCitta":0.0,"lonMappaCitta":0.0,"localita":{"nomeLungo":"NAPOLI MERGELLINA","nomeBreve":"NA Mergellina","label":"","id":"S09105"},"esterno":false,"offsetX":0,"offsetY":0,"nomeCitta":"A"},{"codReg":18,"tipoStazione":3,"dettZoomStaz":[],"pstaz":[],"mappaCitta":{"urlImagePinpoint":"","urlImageBaloon":""},"codiceStazione":"S09107","codStazione":"S09107","lat":40.847807,"lon":14.244022,"latMappaCitta":0.0,"lonMappaCitta":0.0,"localita":{"nomeLungo":"NAPOLI MONTESANTO","nomeBreve":"NA Montesanto","label":"","id":"S09107"},"esterno":false,"offsetX":0,"offsetY":0,"nomeCitta":"A"},{"codReg":18,"tipoStazione":3,"dettZoomStaz":[],"pstaz":[],"mappaCitta":{"urlImagePinpoint":"","urlImageBaloon":""},"codiceStazione":"S09106","codStazione":"S09106","lat":40.838506,"lon":14.232974,"latMappaCitta":0.0,"lonMappaCitta":0.0,"localita":{"nomeLungo":"PIAZZA AMEDEO","nomeBreve":"Piazza Amedeo","label":"","id":"S09106"},"esterno":false,"offsetX":0,"offsetY":0,"nomeCitta":"A"},{"codReg":18,"tipoStazione":1,"dettZoomStaz":[{"codiceStazione":"S09218","zoomStartRange":8,"zoomStopRange":9,"pinpointVisibile":true,"pinpointVisible":true,"labelVisibile":true,"labelVisible":true,"codiceRegione":null},{"codiceStazione":"S09218","zoomStartRange":10,"zoomStopRange":11,"pinpointVisibile":true,"pinpointVisible":true,"labelVisibile":true,"labelVisible":true,"codiceRegione":null}],"pstaz":[],"mappaCitta":{"urlImagePinpoint":"","urlImageBaloon":""},"codiceStazione":"S09218","codStazione":"S09218","lat":40.852933,"lon":14.272908,"latMappaCitta":0.0,"lonMappaCitta":0.0,"localita":{"nomeLungo":"NAPOLI CENTRALE","nomeBreve":"Napoli Centrale","label":"Napoli","id":"S09218"},"esterno":false,"offsetX":20,"offsetY":0,"nomeCitta":"Napoli"},{"codReg":18,"tipoStazione":3,"dettZoomStaz":[],"pstaz":[],"mappaCitta":{"urlImagePinpoint":"","urlImageBaloon":""},"codiceStazione":"S09626","codStazione":"S09626","lat":40.879143,"lon":15.129255,"latMappaCitta":0.0,"lonMappaCitta":0.0,"localita":{"nomeLungo":"CAMPO DI NUSCO","nomeBreve":"Campo di Nusco","label":"","id":"S09626"},"esterno":false,"offsetX":0,"offsetY":0,"nomeCitta":"A"},{"codReg":18,"tipoStazione":3,"dettZoomStaz":[],"pstaz":[],"mappaCitta":{"urlImagePinpoint":"","urlImageBaloon":""},"codiceStazione":"S09505","codStazione":"S09505","lat":41.285869,"lon":14.726853,"latMappaCitta":0.0,"lonMappaCitta":0.0,"localita":{"nomeLungo":"CAMPOLATTARO","nomeBreve":"Campolattaro","label":"","id":"S09505"},"esterno":false,"offsetX":0,"offsetY":0,"nomeCitta":"A"},{"codReg":18,"tipoStazione":3,"dettZoomStaz":[],"pstaz":[],"mappaCitta":{"urlImagePinpoint":"","urlImageBaloon":""},"codiceStazione":"S09101","codStazione":"S09101","lat":40.827586,"lon":14.126163,"latMappaCitta":0.0,"lonMappaCitta":0.0,"localita":{"nomeLungo":"POZZUOLI SOLFATARA","nomeBreve":"Pozzuoli S.","label":"","id":"S09101"},"esterno":false,"offsetX":0,"offsetY":0,"nomeCitta":"A"},{"codReg":18,"tipoStazione":3,"dettZoomStaz":[],"pstaz":[],"mappaCitta":{"urlImagePinpoint":"","urlImageBaloon":""},"codiceStazione":"S09111","codStazione":"S09111","lat":40.871086,"lon":14.122801,"latMappaCitta":0.0,"lonMappaCitta":0.0,"localita":{"nomeLungo":"QUARTO DI MARANO","nomeBreve":"Quarto di Marano","label":"","id":"S09111"},"esterno":false,"offsetX":0,"offsetY":0,"nomeCitta":"A"},{"codReg":18,"tipoStazione":3,"dettZoomStaz":[],"pstaz":[],"mappaCitta":{"urlImagePinpoint":"","urlImageBaloon":""},"codiceStazione":"S09302","codStazione":"S09302","lat":41.06235,"lon":14.30323,"latMappaCitta":0.0,"lonMappaCitta":0.0,"localita":{"nomeLungo":"RECALE","nomeBreve":"Recale","label":"","id":"S09302"},"esterno":false,"offsetX":0,"offsetY":0,"nomeCitta":"A"},{"codReg":18,"tipoStazione":3,"dettZoomStaz":[],"pstaz":[],"mappaCitta":{"urlImagePinpoint":"","urlImageBaloon":""},"codiceStazione":"S09762","codStazione":"S09762","lat":40.872234,"lon":14.482833,"latMappaCitta":0.0,"lonMappaCitta":0.0,"localita":{"nomeLungo":"REVIGLIONE DI SOMMA VESUVIANA","nomeBreve":"Reviglione di S.","label":"","id":"S09762"},"esterno":false,"offsetX":0,"offsetY":0,"nomeCitta":"A"},{"codReg":18,"tipoStazione":3,"dettZoomStaz":[],"pstaz":[],"mappaCitta":{"urlImagePinpoint":"","urlImageBaloon":""},"codiceStazione":"S09204","codStazione":"S09204","lat":41.265177,"lon":14.124949,"latMappaCitta":0.0,"lonMappaCitta":0.0,"localita":{"nomeLungo":"RIARDO","nomeBreve":"Riardo","label":"","id":"S09204"},"esterno":false,"offsetX":0,"offsetY":0,"nomeCitta":"A"}]